Workbook

Sheet Sheet1
A1: Modelo | B1: Bert-score | C1: F1 | D1: Latency | E1: Maquina | F1: BLEU
A2: raulgdp/Mistral-7B-Instruct-v0.3-JEP | B2: ='Mistral-7B-Instruct-v0.3'!K3 -> 76.593103 | C2: ='Mistral-7B-Instruct-v0.3'!K4 -> 31.167857 | D2: ='Mistral-7B-Instruct-v0.3'!K2 -> 6918.1724 | E2: A100 40gb
A3: raulgdp/Mistral-8B-Instruct-2410-009 | B3: ='Mistral-8B-Instruct-2410-009'!K3 -> 79.357143 | C3: ='Mistral-8B-Instruct-2410-009'!K4 -> 35.853846 | D3: ='Mistral-8B-Instruct-2410-009'!K2 -> 6428.5714 | E3: A100 40gb
A4: raulgdp/Llama-3.2-3B-Instruct-JEP | B4: ='Llama-3.2-3B-Instruct-JEP-resul'!K3 -> 74.973077 | C4: ='Llama-3.2-3B-Instruct-JEP-resul'!K4 -> 29.441379 | D4: ='Llama-3.2-3B-Instruct-JEP-resul'!K2 -> 7792.5385 | E4: A100 40gb
A5: raulgdp/Llama-2-7B-Nous-Hermes-llama-JEP | B5: ='Llama-2-7B-Nous-Hermes-llama-JE'!K3 -> 0.738 | C5: ='Llama-2-7B-Nous-Hermes-llama-JE'!K4 -> 0.31133333 | D5: ='Llama-2-7B-Nous-Hermes-llama-JE'!K2 -> 6.6633333 | E5: A100 40gb
A6: raulgdp/OpenHermes-2.5-Mistral-7B-JEP | B6: ='OpenHermes-2.5-Mistral-7B'!K3 -> 75.496296 | C6: ='OpenHermes-2.5-Mistral-7B'!K4 -> 33.157692 | D6: ='OpenHermes-2.5-Mistral-7B'!K2 -> 8692.1429 | E6: A100 40gb
A7: unsloth-Llama3.1-8B | B7: ='Llama3.1_(8B)'!K3 -> 73.834483 | C7: ='Llama3.1_(8B)'!K4 -> 23.466667 | D7: ='Llama3.1_(8B)'!K2 -> 27953.567 | E7: Intel(R) Xeon(R) CPU @ 2.20GHz 12 cores

Sheet Llama-3.2-3B-Instruct-JEP-resul
A1: question | B1: context | C1: expected_answer | D1: predicted_answer | E1: latency | F1: bert_score | G1: f1_score | J1: Promedios
A2: ¿Qué informe documenta la Operación Orión y su impacto en la Comuna 13 de Medellín? | B2: El informe 058‑CI‑01347 «Comuna 13: memorias de un territorio en resistencia» analiza la Operación Orión (octubre de 2002), la coordinación entre fuerza pública y paramilitares, las desapariciones forzadas y detenciones arbitrarias, así como la consolidación posterior del control armado y las resistencias comunitarias. | C2: El informe 058‑CI‑01347 «Comuna 13: memorias de un territorio en resistencia» detalla la Operación Orión y explica por qué este operativo es clave para entender las graves violaciones a los derechos humanos en la Comuna 13. | D2: El informe documenta la Operación Orión como una intervención militar que incluyó la coordinación con grupos paramilitares y resultó en desapariciones forzadas, detenciones arbitrarias y el fortalecimiento de la presencia armada en la Comuna 13 de Medellín. Además, el informe subraya las resistencias comunitarias frente a la violencia y las consecuencias a largo plazo para el territorio y sus habitantes. Estas acciones tuvieron un impacto negativo en la vida cotidiana de los habitantes y en la consolidación de la paz en la región. La resistencia comunitaria es un aspecto clave para entender la | E2: 8961 | F2: 713 | G2: 305 | I2: ejcutado con la A100 | J2: latency | K2: =AVERAGE(E2:E31) -> 7792.5385
A3: ¿Qué informe analiza la relación entre los monocultivos de palma aceitera y caña de azúcar y la profundización del conflicto armado colombiano? | B3: El informe 066‑CI‑00538 «Misión internacional para la verificación del impacto de los agrocombustibles en cinco zonas afectadas por los monocultivos de palma aceitera y caña de azúcar en Colombia» expone cómo la expansión de estos monocultivos—respaldada por actores armados, empresariales y estatales—provocó desplazamientos forzados y pérdida de soberanía territorial en cinco regiones del país. | C3: El informe «Misión internacional para la verificación del impacto de los agrocombustibles» explica de manera directa ese vínculo entre agrocombustibles y conflicto armado. | D3: La relación entre los monocultivos de palma aceitera y caña de azúcar y el conflicto armado colombiano es un tema central en el informe. Se destaca cómo la expansión de estos monocultivos ha sido utilizada como estrategia para consolidar la presencia de actores armados, desplazar a comunidades campesinas y afectar la autonomía local. El informe subraya que los monocultivos han sido utilizados como mecanismo de control territorial, facilitando la llegada de grupos armados ilegales y comprometiendo el acceso a tierras y recursos para las comunidades locales. Además, el informe resalta que la relación entre el | E3: 7681 | F3: 683 | G3: 169 | J3: bert_score | K3: =AVERAGE(F2:F31)/10 -> 74.973077
A4: ¿Cuál es la capital de Japón? | C4: Lo siento, solo puedo responder preguntas relacionadas con el conflicto armado colombiano. | D4: No tengo información relevante para responder a esa pregunta. ¿Puedo ayudarte con algo más? | E4: 1,15 | F4: 716 | G4: 231 | J4: f1_score | K4: =AVERAGE(G2:G31)/10 -> 29.441379
A5: ¿Cuáles son las principales causas estructurales que originaron el conflicto armado colombiano de acuerdo con la Comisión de la Verdad? | B5: La Comisión señala la concentración de la tierra, la exclusión política y social, la desigualdad económica y la débil presencia estatal—especialmente en zonas rurales—como factores estructurales que propiciaron la aparición y persistencia de los actores armados. | C5: Las causas estructurales incluyen la marcada concentración de la propiedad de la tierra, la exclusión política y social de amplios sectores, la desigualdad económica y la ausencia de un Estado eficaz en muchos territorios rurales. | D5: El conflicto armado colombiano tiene sus raíces en causas estructurales como la concentración de la tierra, la exclusión política y social, la desigualdad económica y la débil presencia estatal en zonas rurales. Estas condiciones facilitan la aparición y consolidación de grupos armados que buscan controlar el territorio y la economía para sus intereses. La falta de acceso a tierras, oportunidades y justicia social agudiza la violencia y limita las oportunidades de integración social y económica de las comunidades afectadas. Por lo tanto, es fundamental abordar estas causas estructurales para prevenir la repetición de | E5: 7789 | F5: 762 | G5: 234
A6: ¿Qué dice este informe 058-CI-00661 «Informe sobre el conflicto social y armado en el suroeste de Antioquia» sobre las causas estructurales del conflicto armado y sus recomendaciones para la no repetición? | B6: El informe identifica como causas estructurales del conflicto la desigualdad en el acceso a la tierra, la exclusión política, la represión de los movimientos sociales, la concentración del poder económico y político, y la criminalización de la protesta. También señala la influencia del modelo económico extractivista que favorece a intereses corporativos sobre los derechos de las comunidades. Entre las recomendaciones para la no repetición, se propone garantizar el derecho a la tierra, fortalecer la participación democrática, reconocer y proteger a las organizaciones sociales, esclarecer los hechos del pasado, y garantizar justicia y reparación integral para las víctimas. | C6: El informe atribuye el conflicto a causas estructurales como la concentración de la tierra, exclusión política, represión estatal y modelo económico extractivista. Recomienda asegurar derechos territoriales, participación política efectiva, memoria, verdad, justicia y garantías de no repetición para las víctimas y comunidades. | D6: Este informe 058-CI-00661 identifica como causas estructurales del conflicto armado en el suroeste de Antioquia la desigualdad en el acceso a la tierra, la exclusión política, la represión de los movimientos sociales, la concentración del poder económico y político, y la criminalización de la protesta. Entre sus recomendaciones para la no repetición, el informe propone garantizar el derecho a la tierra, fortalecer la participación democrática, reconocer y proteger a las organizaciones sociales, esclarecer los hechos del pasado y asegurar justicia y reparación integral para las víctimas. Estas recomend | E6: 7,87 | F6: 0,76 | G6: 364
A7: ¿Cuáles son los hallazgos principales del informe 058-CI-00662 «Memoria y construcción de paz en el sector cooperativo del oriente antioqueño: estudio de caso de las cooperativas Coogranada, Creafam, Confiar, Pío XII y Coosanluis entre 1991 y 2016» sobre el conflicto armado colombiano? | B7: El informe 058-CI-00662 «Memoria y construcción de paz en el sector cooperativo» señala que el Movimiento Solidario y Cooperativo del Oriente Antioqueño fue uno de los sectores más golpeados por el conflicto armado. A pesar de ello, cumplió un papel protagónico al desplegar acciones de resistencia y apoyo a las comunidades desplazadas. Las cooperativas enfrentaron tomas armadas, desplazamiento forzado, confinamiento, extorsión e intimidación, pero lograron mantener su operación mediante estrategias de sostenibilidad, expansión y fortalecimiento del tejido social. Se destaca el apoyo a las personas asociadas mediante la condonación de deudas, créditos especiales y reconstrucción física de los municipios. | C7: El informe documenta que las cooperativas del Oriente Antioqueño fueron gravemente afectadas por el conflicto armado mediante desplazamientos forzados, violencia directa a empleados y asociados, y presiones de actores armados. No obstante, desempeñaron un papel clave en la resistencia civil, apoyando a comunidades desplazadas y contribuyendo a la reconstrucción del tejido social mediante estrategias económicas solidarias y acciones comunitarias. | D7: Entre los hallazgos principales del informe se destaca la grave afectación del sector cooperativo del oriente antioqueño por parte del conflicto armado colombiano. Las cooperativas enfrentaron desplazamiento forzado, toma armada, extorsión y confinamiento, pero lograron resistir y fortalecer su tejido social a través de la construcción de memoria, el apoyo a las comunidades desplazadas y la implementación de programas de sostenibilidad. Además, las cooperativas fueron fundamentales para la reconstrucción física y social de los municipios afectados. La resistencia y el compromiso con la paz se consolidaron a través de la solid | E7: 7907 | F7: 759 | G7: 0,28
A8: ¿Qué tipo de violencia vivieron las cooperativas del Oriente Antioqueño entre 1991 y 2016 según el informe? | B8: El informe 058-CI-00662 «Memoria y construcción de paz en el sector cooperativo» detalla que las cooperativas fueron blanco de diversas acciones violentas durante el conflicto armado. Estas incluyeron asesinatos de empleados, familiares y asociados; robos e intentos de extorsión; y violencia psicológica e intimidación por parte de grupos armados. Estos actos no solo afectaron el funcionamiento de las cooperativas, sino que también contribuyeron al empobrecimiento de sus comunidades asociadas y al desplazamiento forzado masivo. | C8: Las cooperativas del Oriente Antioqueño vivieron asesinatos selectivos de su personal y asociados, robos, extorsión, amenazas e intimidación psicológica por parte de actores armados. Estas formas de violencia afectaron gravemente su funcionamiento institucional, provocaron desplazamiento forzado y contribuyeron a la descomposición del tejido social de las comunidades cooperadas. | D8: Entre 1991 y 2016, las cooperativas del Oriente Antioqueño sufrieron violencia de diversos tipos, como asesinatos, robo, extorsión y violencia psicológica, a manos de actores armados ilegales. Estas acciones no solo afectaron la vida de los empleados y sus familias, sino que también contribuyeron al deterioro social y económico de las comunidades asociadas, exacerbando el desplazamiento forzado y el empobrecimiento. La violencia ejercida en estas cooperativas fue un factor estructural del conflicto armado colombiano que debilitó la institucionalidad y la organización social de | E8: 7848 | F8: 795 | G8: 336
A9: ¿Qué dice este informe 365-CI-00941 La participación de pueblos indígenas en justicia transicional - ¿oportunidad de cambios? Aprendizajes de Colombia sobre las causas estructurales del conflicto armado y sus recomendaciones para la no repetición? | B9: El informe 365-CI-00941 La participación de pueblos indígenas en justicia transicional resalta que una reconciliación multinacional, multicultural y multiétnica es esencial para asegurar la no repetición. Plantea que deben transformarse las estructuras que perpetúan la dominación étnica y que el diálogo debe incluir múltiples dimensiones socio-culturales【4:8†source】. | C9: El informe propone dialogar y revisar estructuras socio-culturales como medidas claves para la no repetición y aborda las causas estructurales del conflicto desde la perspectiva de dominación étnica y falta de reconocimiento multicultural. | D9: Entre las causas estructurales del conflicto armado colombiano se identifican la desigualdad étnica, la falta de representación y el acceso limitado a los derechos colectivos de las comunidades indígenas. Para evitar la repetición, el informe recomienda fortalecer la participación de los pueblos indígenas en los procesos de paz, reconocer su identidad y derechos, y promover políticas inclusivas y equitativas que garanticen la justicia transicional y la no repetición del conflicto. Además, destaca la necesidad de un diálogo intercultural y multietnico como base para la construcción de | E9: 7768 | F9: 739 | G9: 267
A10: ¿Cómo el sistema de justicia transicional puede beneficiar a los pueblos indígenas en el contexto colombiano según el informe 365-CI-00941? | B10: El Sistema Integral de Verdad, Justicia, Reparación y No Repetición (SIVJRNR) está diseñado para satisfacer el derecho a la verdad, justicia y reparación, aunque la implementación efectiva es cuestionada por la falta de recursos y capacitación adecuada【4:7†source】. | C10: El sistema de justicia transicional tiene el potencial de beneficiar a los pueblos indígenas al proporcionar verdad, justicia y reparación, pero enfrenta desafíos significativos en su implementación debido a recursos limitados. | D10: El sistema de justicia transicional en el contexto colombiano puede beneficiar a los pueblos indígenas mediante la creación de mecanismos que garantizan la protección de sus derechos, la reparación integral de las violaciones y la no repetición de la violencia. Sin embargo, se enfrenta a desafíos como la falta de recursos, capacitación y apoyo institucional. La implementación efectiva requiere fortalecimiento institucional, capacitación para actores estatales y comunidades, y reconocimiento y respeto a los derechos de las poblaciones indígenas. Además, es fundamental abordar las causas estructurales de la viol | E10: 7758 | F10: 0,77 | G10: 286
A11: ¿Cuáles son los hallazgos principales del informe «365-CI-00942 Bitácora de la guerra sucia» sobre graves violaciones a los derechos humanos e infracciones al Derecho Internacional Humanitario cometidas en el Departamento del Cauca entre los años 2006–2016? | B11: «365-CI-00942 Bitácora de la guerra sucia» es un informe que evidencia violaciones sistemáticas a los derechos humanos cometidas por diferentes actores armados en el Departamento del Cauca, principalmente por la Fuerza Pública, grupos paramilitares y grupos sucesores del paramilitarismo. Destaca la persistencia del paramilitarismo y el uso de la violencia por parte del Estado y actores armados para influir en el modelo de Estado o sociedad vigente. Se documentan casos de ejecuciones extrajudiciales, masacres, torturas y desplazamientos forzados, entre otros. | C11: El informe «365-CI-00942 Bitácora de la guerra sucia» revela graves violaciones a los derechos humanos en el Cauca, cometidas por la Fuerza Pública, grupos paramilitares y sus sucesores, incluyendo ejecuciones extrajudiciales, masacres, torturas y desplazamientos forzados; evidencia la persistencia del paramilitarismo y el uso de la violencia para mantener el statu quo social y político. | D11: Entre los hallazgos principales del informe se destacan: la persistencia del paramilitarismo en el Departamento del Cauca, la violencia sistemática ejercida por diferentes actores armados contra la población civil, especialmente por la Fuerza Pública y grupos paramilitares. Se evidencian graves violaciones al Derecho Internacional Humanitario, como ejecuciones extrajudiciales, masacres, torturas y desplazamientos forzados. El informe también señala que estas violaciones están relacionadas con el uso de la fuerza como herramienta de control social y política, afectando profundamente la vida y los derechos de las comunidades afectadas. Además, | E11: 7892 | F11: 807 | G11: 389
A12: ¿Cuáles son los hallazgos principales del informe «365-CI-01666 Aportes para la implementación del enfoque extraterritorial» sobre el conflicto armado colombiano? | B12: El informe «365-CI-01666 Aportes para la implementación del enfoque extraterritorial» de la Comisión para el Esclarecimiento de la Verdad, la Convivencia y la No Repetición destaca la persistencia de graves violaciones a los derechos humanos y al Derecho Internacional Humanitario durante el conflicto armado colombiano, incluyendo desplazamiento forzado, desapariciones forzadas, violencia sexual, asesinatos y reclutamiento de menores. Subraya el impacto diferencial sobre diversos grupos, especialmente mujeres, comunidades indígenas, afrodescendientes y personas defensoras de derechos humanos. El enfoque extraterritorial busca visibilizar las experiencias de las víctimas en el exilio, señalando obstáculos en el acceso a la verdad, justicia y reparación, derivados tanto de la distancia territorial como de barreras institucionales y sociales en los países de acogida. | C12: El informe «365-CI-01666 Aportes para la implementación del enfoque extraterritorial» señala que el conflicto armado generó violaciones graves a los derechos humanos que afectaron desproporcionadamente a grupos vulnerables. Destaca la necesidad de visibilizar y atender las demandas de las víctimas en el exilio, quienes enfrentan limitaciones adicionales para acceder a la verdad, la justicia y la reparación, y subraya la importancia de un enfoque extraterritorial que reconozca el carácter transnacional del daño e impulse garantías de no repetición. | D12: Los hallazgos principales del informe son: la persistencia de graves violaciones a los derechos humanos y al Derecho Internacional Humanitario, el desplazamiento forzado, desapariciones forzadas, violencia sexual y asesinatos. Destaca el impacto diferencial sobre comunidades vulnerables, como mujeres, indígenas, afrodescendientes y personas defensoras de derechos humanos. Señala la necesidad de visibilizar las experiencias de las víctimas en el exilio y las barreras para acceder a la verdad, justicia y reparación. Además, resalta la importancia del enfoque extraterritorial para abord | E12: 7839 | F12: 759 | G12: 365
A13: ¿Cuáles son los hallazgos principales del informe «365-CI-01666 Aportes para la implementación del enfoque extraterritorial» sobre el conflicto armado colombiano? | B13: El informe «365-CI-01666 Aportes para la implementación del enfoque extraterritorial» argumenta que las víctimas exiliadas como resultado del conflicto armado colombiano poseen necesidades específicas derivadas de su desplazamiento internacional, sufriendo la pérdida de derechos, disolución de tejidos comunitarios y obstáculos a la participación política en Colombia. Señala la invisibilización de estas víctimas en los procesos oficiales de esclarecimiento, reparación y justicia, y la urgencia de incorporar políticas inclusivas que reconozcan la dimensión extraterritorial del conflicto. | C13: El informe «365-CI-01666 Aportes para la implementación del enfoque extraterritorial» identifica que las víctimas en el exilio han sido sistemáticamente invisibilizadas en los procesos de verdad y reparación y enfrentan barreras adicionales para acceder a sus derechos. Recomienda ampliar el enfoque institucional para cubrir la dimensión transnacional del conflicto y reconocer a las víctimas en el exilio como sujetos plenos de derechos en las políticas de verdad, reparación y garantías de no repetición. | D13: Entre los hallazgos principales del informe se destaca la necesidad de reconocer la vulnerabilidad de las víctimas exiliadas en el contexto del conflicto armado colombiano, quienes enfrentan desplazamiento, pérdida de derechos y desintegración social. Se enfatiza la invisibilización en los procesos de justicia y reparación, así como la urgencia de implementar políticas públicas que atiendan las necesidades específicas de las víctimas exiliadas, promoviendo su participación activa en la construcción de la paz y la restitución de derechos en el extraterritorio. El informe resalta la importancia de una respuesta | E13: 7879 | F13: 706 | G13: 233
A14: ¿Qué señala el informe «365-CI-01666 Aportes para la implementación del enfoque extraterritorial» sobre las causas estructurales del conflicto armado y sus recomendaciones para la no repetición? | B14: El informe «365-CI-01666 Aportes para la implementación del enfoque extraterritorial» explica que entre las causas estructurales del conflicto armado colombiano se encuentran la exclusión política, la desigualdad social y económica, la concentración de la tierra y la falta de garantías para el ejercicio de derechos fundamentales. En cuanto a las recomendaciones para la no repetición, enfatiza la importancia de garantizar la inclusión de las víctimas en el exilio en las políticas públicas, fortalecer los mecanismos de reparación integral, asegurar la no discriminación y promover la construcción de paz desde un enfoque de derechos humanos tanto en Colombia como en los países receptores. | C14: El informe «365-CI-01666 Aportes para la implementación del enfoque extraterritorial» identifica como causas estructurales del conflicto factores como la exclusión política, la concentración de la tierra, la desigualdad social y la falta de garantías de derechos. Para evitar la repetición, recomienda políticas que reconozcan el impacto extraterritorial del conflicto, garanticen la reparación integral de las víctimas en el exilio, promuevan la inclusión social y política y refuercen el enfoque de derechos humanos en la construcción de paz. | D14: El informe señala que el conflicto armado colombiano tiene causas estructurales como la exclusión política, la desigualdad y la concentración de la tierra. Para evitar la repetición de estos hechos, recomienda fortalecer la inclusión de las víctimas en el exilio, asegurar su reparación integral, promover la no discriminación y fomentar la construcción de paz desde los derechos humanos tanto en Colombia como en los países de exilio. Estas recomendaciones buscan abordar las causas profundas del conflicto y garantizar la protección de los derechos de las personas en el exterior. | E14: 7257 | F14: 824 | G14: 369
A15: ¿Cuáles son los hallazgos principales del informe «748-CI-00629 Contextos explicativos del desplazamiento forzado en el sur del Tolima: impactos sobre el territorio y la territorialidad 1958–2018» sobre el conflicto armado colombiano? | B15: El informe «748-CI-00629 Contextos explicativos del desplazamiento forzado en el sur del Tolima: impactos sobre el territorio y la territorialidad 1958–2018» señala que el territorio del sur del Tolima fue escenario de múltiples disputas entre grupos armados ilegales, generando un clima constante de amenaza, persecución y violencia. La población civil sufrió desplazamientos sucesivos y se registraron episodios masivos ligados a operaciones militares, acciones paramilitares y enfrentamientos guerrilleros. Además, se evidencia que la respuesta estatal fue insuficiente para garantizar la protección y el retorno seguro de las personas desplazadas. | C15: El informe «748-CI-00629 Contextos explicativos del desplazamiento forzado en el sur del Tolima: impactos sobre el territorio y la territorialidad 1958–2018» revela que la multiplicidad de actores armados y la falta de protección estatal ocasionaron desplazamientos masivos y recurrentes, afectando particularmente a comunidades rurales, y subraya la necesidad de fortalecer la presencia y respuesta institucional para evitar la repetición de estos hechos violentos. | D15: Entre los hallazgos principales del informe se destaca que el sur del Tolima estuvo marcado por el conflicto armado colombiano, caracterizado por la presencia de grupos armados ilegales y la violencia ejercida contra la población civil. El desplazamiento forzado fue un fenómeno común, especialmente en zonas rurales y comunidades campesinas, quienes sufrieron amenazas, persecución y violencia, además de enfrentar dificultades en el acceso a servicios básicos y protección estatal. El informe también resalta la persistencia de violaciones a los derechos humanos y la falta de garantías para el retorno seguro de las | E15: 7,75 | F15: 736 | G15: 266
A16: ¿Cuáles fueron los principales episodios de desplazamiento forzado documentados en el informe «748-CI-00629 Contextos explicativos del desplazamiento forzado en el sur del Tolima: impactos sobre el territorio y la territorialidad 1958–2018» entre 1958 y 2018? | B16: El informe «748-CI-00629 Contextos explicativos del desplazamiento forzado en el sur del Tolima: impactos sobre el territorio y la territorialidad 1958–2018» describe casos emblemáticos de desplazamiento forzado como el ocurrido en el municipio de Planadas durante los años ochenta y noventa, cuando cientos de familias abandonaron sus hogares debido a confrontaciones entre el Ejército y las fuerzas guerrilleras. Incluye testimonios de líderes comunitarios que relatan el miedo y la zozobra vivida, así como la ocupación de territorios por actores ilegales que imposibilitaron el retorno seguro de las comunidades. | C16: En el informe «748-CI-00629 Contextos explicativos del desplazamiento forzado en el sur del Tolima: impactos sobre el territorio y la territorialidad 1958–2018», los principales episodios documentados incluyen acciones militares y hostigamientos de grupos armados ilegales en municipios como Planadas, donde las comunidades se vieron obligadas a abandonar sus tierras ante el riesgo inminente de violencia, afectando profundamente su arraigo territorial y proyecto de vida. | D16: Entre 1958 y 2018, los principales episodios de desplazamiento forzado en el sur del Tolima documentados en el informe incluyen: el desplazamiento masivo de familias de Planadas durante los años ochenta y noventa, resultante de enfrentamientos entre el Ejército y las guerrillas, y testimonios de líderes comunitarios que narran la ocupación de territorios por actores ilegales y la imposibilidad de retorno seguro de las comunidades afectadas. Estos eventos tuvieron un impacto profundo en la territorialidad y la identidad de las comunidades del sur del Tolima. El informe destaca la persistencia | E16: 7775 | F16: 747 | G16: 293
A17: ¿Qué relación establece el informe «748-CI-00629 Contextos explicativos del desplazamiento forzado en el sur del Tolima: impactos sobre el territorio y la territorialidad 1958–2018» entre el control territorial por parte de actores armados y las transformaciones en las dinámicas agrarias y sociales del sur del Tolima? | B17: El informe «748-CI-00629 Contextos explicativos del desplazamiento forzado en el sur del Tolima: impactos sobre el territorio y la territorialidad 1958–2018» vincula en varios apartados el control territorial ejercido por actores armados ilegales con la imposición de nuevas dinámicas económicas y sociales. Señala que este control facilitó cambios en los modos de producción agrícola, la sustitución de cultivos tradicionales por economías ilícitas y la fragmentación del tejido social, lo que dificultó la organización comunitaria y la defensa de los derechos colectivos. | C17: El informe «748-CI-00629 Contextos explicativos del desplazamiento forzado en el sur del Tolima: impactos sobre el territorio y la territorialidad 1958–2018» establece que la presencia y control territorial de grupos armados ilegales provocaron transformaciones en la estructura agraria, el surgimiento de economías ilícitas y una mayor vulnerabilidad de las comunidades frente a la violencia y la desprotección estatal. | D17: El informe establece que el control territorial por parte de actores armados ilegales en el sur del Tolima llevó a transformaciones significativas en las dinámicas agrarias y sociales. Se identifican cambios en los modos de producción, la sustitución de cultivos tradicionales por economías ilícitas, la fragmentación del tejido social y la imposición de nuevas estructuras económicas que han afectado negativamente la territorialidad y la organización comunitaria en el territorio. Estas transformaciones han sido consecuencia directa del control territorial ejercido por actores armados, que facilitaron la imposición de economías ilegales y la desartic | E17: 7803 | F17: 747 | G17: 288
A18: ¿Qué dice el informe «748-CI-00855 La sombra oscura del banano: Urabá. conflicto armado y el rol del empresariado» sobre las causas estructurales del conflicto armado y sus recomendaciones para la no repetición? | B18: El informe «748-CI-00855 La sombra oscura del banano: Urabá. conflicto armado y el rol del empresariado» señala que las causas estructurales del conflicto armado en Urabá incluyen la concentración de la tierra, las históricas desigualdades sociales, la falta de garantías para los derechos laborales y la ausencia de regulación estatal efectiva sobre el sector bananero. Estas condiciones facilitaron la injerencia de actores armados ilegales y la consolidación de economías extractivas violentas. Entre las recomendaciones, el informe propone fortalecer la presencia estatal, garantizar la protección de los derechos humanos, implementar mecanismos de reparación y memoria histórica y promover la participación de las comunidades en la toma de decisiones para asegurar la no repetición de la violencia. | C18: El informe «748-CI-00855 La sombra oscura del banano: Urabá. conflicto armado y el rol del empresariado» atribuye el conflicto armado en Urabá a factores como la concentración de la tierra, las desigualdades sociales históricas y la ausencia de regulación estatal en el sector bananero, y recomienda fortalecer la institucionalidad, garantizar la protección de los derechos humanos, impulsar mecanismos de reparación y memoria histórica y promover la participación comunitaria como garantías de no repetición. | D18: El informe «748-CI-00855 La sombra oscura del banano: Urabá. conflicto armado y el rol del empresariado» identifica como causas estructurales del conflicto armado en Urabá la concentración de la tierra, desigualdades sociales y la falta de regulación estatal sobre el sector bananero. Estas condiciones facilitaron la presencia de actores armados ilegales y la violencia económica. Entre sus recomendaciones para la no repetición, el informe destaca la necesidad de fortalecer la presencia estatal, garantizar derechos humanos, implementar mecanismos de reparación y memoria histó | E18: 7816 | F18: 904 | G18: 453
A19: ¿Cuáles son los hallazgos principales del informe «748-CI-00857 Análisis policías víctimas del conflicto armado interno» sobre el conflicto armado colombiano? | B19: El informe «748-CI-00857 Análisis policías víctimas del conflicto armado interno» presenta un análisis sobre el impacto del conflicto en los miembros de la Policía Nacional, destacando cifras de homicidios, desapariciones forzadas, secuestros y otros hechos victimizantes a lo largo de varias décadas. Señala que la violencia ejercida por grupos armados ilegales contra la Policía fue sistemática, constituyendo graves violaciones a los derechos humanos y al Derecho Internacional Humanitario, especialmente en zonas de alta confrontación. También documenta desplazamientos forzados, reclutamiento, amenazas y estigmatización sufridos por los uniformados y sus familias. | C19: El informe «748-CI-00857 Análisis policías víctimas del conflicto armado interno» revela que los policías sufrieron múltiples formas de victimización, incluyendo homicidios, desapariciones forzadas, secuestros, desplazamientos forzados, amenazas y estigmatización, perpetradas de manera sistemática por grupos armados ilegales y generando graves impactos en los uniformados y sus familias. | D19: Entre los hallazgos principales del informe se encuentran: la alta incidencia de homicidios, desapariciones forzadas y secuestros cometidos contra miembros de la Policía en el contexto del conflicto armado colombiano; la sistemática violación de los derechos humanos y del Derecho Internacional Humanitario por parte de actores armados ilegales; la afectación a la integridad y seguridad de los uniformados, así como el impacto en sus familias; y la persistencia de desplazamientos forzados y reclutamientos ilegales. Estos hallazgos reflejan la gravedad de la violencia sufrida por la Policía | E19: 7916 | F19: 731 | G19: 326
A20: ¿Cuáles son los principales tipos de victimización sufridos por policías durante el conflicto armado según el informe «748-CI-00857 Análisis policías víctimas del conflicto armado interno»? | B20: El informe «748-CI-00857 Análisis policías víctimas del conflicto armado interno» detalla que los miembros de la Policía Nacional fueron víctimas de homicidios selectivos, desapariciones forzadas, secuestros, desplazamientos forzados, amenazas, atentados y ataques directos a instalaciones policiales. Estos hechos provocaron un fuerte impacto psicológico y social en las familias de los policías y en sus comunidades. | C20: El informe «748-CI-00857 Análisis policías víctimas del conflicto armado interno» establece que los policías fueron víctimas de homicidios selectivos, desapariciones forzadas, secuestros, desplazamientos forzados, amenazas y ataques a instalaciones policiales, lo que generó daños a nivel psicológico, social y familiar. | D20: Los principales tipos de victimización sufridos por policías durante el conflicto armado incluyen homicidios selectivos, desapariciones forzadas, secuestros, desplazamientos forzados, amenazas y ataques directos a instalaciones policiales. Estas acciones han provocado graves impactos en la seguridad y bienestar de las familias y la comunidad policial. Además, el informe destaca la vulnerabilidad de los policías frente a la violencia y el impacto psicológico que se extiende por sus hogares y comunidades. La victimización también se manifestó en ataques a infraestructura policial y afectación de procesos de justicia | E20: 7826 | F20: 763 | G20: 344
A21: ¿Qué dice el informe «119-CI-00336 La maldita tierra: guerrilla, paramilitares, mineras y conflicto armado en el departamento del Cesar» sobre las causas estructurales del conflicto armado y sus recomendaciones para la no repetición? | B21: El informe «119-CI-00336 La maldita tierra: guerrilla, paramilitares, mineras y conflicto armado en el departamento del Cesar» identifica factores como la inequidad en la tenencia de la tierra, la influencia desmedida de élites económicas y políticas, y la falta de intervención estatal efectiva como causas estructurales. Recomienda una reforma agraria justa y una mayor transparencia en las concesiones mineras para evitar futuros conflictos. | C21: El informe «119-CI-00336 La maldita tierra: guerrilla, paramilitares, mineras y conflicto armado en el departamento del Cesar» sugiere que la resolución del conflicto armado requiere abordar profundamente la disparidad en la distribución de tierras y controlar el poder excesivo de las élites locales. Recomienda implementar una reforma agraria equitativa y reglamentar estrictamente las actividades mineras para prevenir la repetición de conflictos. | D21: El informe señala que la inequidad en la tenencia de la tierra, la concentración de la tierra entre pocos actores económicos y políticos y la ausencia de políticas públicas efectivas como la reforma agraria y la regulación de las concesiones mineras son las causas estructurales del conflicto armado en el Cesar. Para la no repetición, el informe recomienda fortalecer la protección de los derechos de las comunidades campesinas y afrodescendientes, implementar políticas de inclusión social y económica y garantizar la participación efectiva de las comunidades en los procesos de toma de decisiones sobre el | E21: 7751 | F21: 741 | G21: 255
A22: ¿Cuáles son los hallazgos principales del informe «119-CI-00339 Tierra y carbón en la vorágine del Gran Magdalena: los casos de las parcelaciones de El Toco, El Platanal y Santa Fe» sobre el conflicto armado colombiano? | B22: El informe «119-CI-00339 Tierra y carbón en la vorágine del Gran Magdalena: los casos de las parcelaciones de El Toco, El Platanal y Santa Fe» describe casos emblemáticos de despojo que se combinaron con acciones contrainsurgentes y un reordenamiento violento del territorio para la transición a economías carboníferas y agroindustriales. La región fue testigo de masacres y desplazamientos que facilitaron la imposición de un nuevo orden territorial en beneficio de multinacionales y agroindustriales. Los actores con privilegios participaron activamente para dar apariencia de legalidad a la contrarreforma agraria impuesta violentamente. | C22: El informe «119-CI-00339 Tierra y carbón en la vorágine del Gran Magdalena: los casos de las parcelaciones de El Toco, El Platanal y Santa Fe» revela un patrón sistemático de despojo y desplazamiento forzado, impulsado por intereses económicos relacionados con la minería y la agroindustria, facilitado por acciones paramilitares y avalado por élites políticas y económicas. Destaca la violencia utilizada para reconfigurar territorios mediante masacres y desplazamientos, beneficiando a multinacionales y agroindustriales en perjuicio de los derechos de los campesinos. | D22: Entre los hallazgos principales del informe se destacan los casos de despojo de tierras y parcelaciones en zonas estratégicas del Gran Magdalena, especialmente en El Toco, El Platanal y Santa Fe, afectadas por el conflicto armado colombiano. Se identifican las masacres y desplazamientos como parte de un plan estratégico para facilitar la transición de economías tradicionales a economías carboníferas y agroindustriales, con la participación activa de actores económicos y políticos que apoyaron la contrarreforma agraria impuesta violentamente. Los despojos de tierras se combinaron con | E22: 7723 | F22: 0,75 | G22: 325
A23: ¿Qué papel jugaron los paramilitares en la reconfiguración del territorio en el Gran Magdalena según el informe «119-CI-00339 Tierra y carbón en la vorágine del Gran Magdalena: los casos de las parcelaciones de El Toco, El Platanal y Santa Fe»? | B23: El informe «119-CI-00339 Tierra y carbón en la vorágine del Gran Magdalena: los casos de las parcelaciones de El Toco, El Platanal y Santa Fe» detalla que los paramilitares, bajo la dirección de líderes como Jorge 40, llevaron a cabo homicidios selectivos y masacres que resultaron en desplazamientos masivos y despojo de tierras. Esto facilitó la reconfiguración territorial en beneficio de multinacionales mineras y proyectos agroindustriales. | C23: El informe «119-CI-00339 Tierra y carbón en la vorágine del Gran Magdalena: los casos de las parcelaciones de El Toco, El Platanal y Santa Fe» establece que los paramilitares jugaron un papel crucial en la reconfiguración violenta del territorio, beneficiando a multinacionales mineras y proyectos agroindustriales mediante masacres y desplazamientos orquestados por liderazgos como el de Jorge 40 y respaldados por alianzas político-económicas. | D23: Los paramilitares jugaron un papel crucial en la reconfiguración del territorio del Gran Magdalena mediante la implementación de estrategias de desplazamiento forzado y despojo de tierras. A través de actos de violencia sistemática, como homicidios selectivos y masacres, los paramilitares permitieron la expulsión de comunidades campesinas y la transferencia de tierras a actores económicos extranjeros, especialmente mineras y agroindustriales, en un contexto de violencia estructural que ha afectado profundamente la población local y el medio ambiente. Este proceso ha sido parte de la estrategia de control territorial y expl | E23: 7,82 | F23: 735 | G23: 297
A24: ¿Qué informe describe la creación del Consejo de Conciliación y Desarrollo Social de San Luis (Antioquia) como estrategia comunitaria para salvar vidas en plena guerra? | B24: El informe «058-CI-00627 Un pueblo que se juntó para salvar vidas en la guerra: Consejo de Conciliación y Desarrollo Social de San Luis, Antioquia» analiza cómo la comunidad de San Luis impulsó acuerdos humanitarios entre 1996 y 2000 para mitigar secuestros, desplazamientos y asesinatos, convirtiéndose en un modelo de paz territorial. | C24: El informe «058-CI-00627 Un pueblo que se juntó para salvar vidas en la guerra: Consejo de Conciliación y Desarrollo Social de San Luis, Antioquia» es el que aborda detalladamente esa experiencia comunitaria. | D24: El informe «058-CI-00627 Un pueblo que se juntó para salvar vidas en la guerra: Consejo de Conciliación y Desarrollo Social de San Luis, Antioquia» describe cómo, en plena guerra, la comunidad de San Luis, Antioquia, adoptó una estrategia comunitaria que buscaba salvar vidas mediante la creación de un Consejo de Conciliación y Desarrollo Social. Este modelo se basó en acuerdos humanitarios entre diferentes actores armados, con el objetivo de mitigar secuestros, desplazamientos y asesinatos. A través de la participación activa de la comunidad, el Consejo logró | E24: 7845 | F24: 795 | G24: 426
A25: ¿Cuál informe estudia el impacto del conflicto armado en las cooperativas Coogranada, Creafam, Confiar, Pío XII y Coosanluis en el Oriente antioqueño entre 1991 y 2016? | B25: El informe «058-CI-00662 Memoria y construcción de paz en el sector cooperativo del Oriente Antioqueño» muestra cómo las cooperativas Coogranada, Creafam, Confiar, Pío XII y Coosanluis sufrieron asesinatos, extorsiones y desplazamientos entre 1991 y 2016, así como su resistencia y aporte a la reconstrucción del tejido social mediante la economía solidaria. | C25: El informe «058-CI-00662 Memoria y construcción de paz en el sector cooperativo del Oriente Antioqueño» analiza precisamente la violencia y la resiliencia de dichas cooperativas. | D25: El informe «058-CI-00662 Memoria y construcción de paz en el sector cooperativo del Oriente Antioqueño» estudia el impacto del conflicto armado en las cooperativas Coogranada, Creafam, Confiar, Pío XII y Coosanluis, destacando su resistencia y aporte a la reconstrucción del tejido social mediante la economía solidaria. Las cooperativas sufrieron asesinatos, extorsiones y desplazamientos entre 1991 y 2016. [Fuente: 11] * Fuente: 11: *Autor: José Rafael Salazar, Editor: Universidad de Antioquia | E25: 7824 | F25: 792 | G25: 367
A26: ¿Qué informe detalla la connivencia entre élites locales, fuerza pública y paramilitares en las zonas 1 y 2 del suroeste antioqueño y las violaciones sistemáticas a los derechos humanos allí cometidas? | B26: El informe «058-CI-00844 Paramilitarismo e impunidad: violaciones a los DD. HH. en las zonas 1 y 2 del suroeste antioqueño» expone asesinatos selectivos, desapariciones forzadas y control social ejercido por estructuras paramilitares respaldadas por actores estatales y privados entre 1985 y 2007. | C26: El informe «058-CI-00844 Paramilitarismo e impunidad: violaciones a los DD. HH. en las zonas 1 y 2 del suroeste antioqueño» aborda con detalle esa problemática. | D26: En el informe «058-CI-00844 Paramilitarismo e impunidad: violaciones a los DD. HH. en las zonas 1 y 2 del suroeste antioqueño», se describe la connivencia entre élites locales, fuerza pública y paramilitares. Este vínculo permitió el control territorial, la impunidad y la perpetuación de violaciones sistemáticas a los derechos humanos en las zonas 1 y 2 del suroeste antioqueño. Los actores estatales y privados, junto con los paramilitares, ejecutaron asesinatos selectivos, desapariciones forzadas y manipulación de la | E26: 7774 | F26: 0,81 | G26: 434
A27: ¿Cuál es la distancia entre la Tierra y la Luna? | C27: Lo siento, solo puedo responder preguntas relacionadas con el conflicto armado colombiano. | D27: La distancia entre la Tierra y la Luna es aproximadamente 384.400 kilómetros, según los datos más actualizados. Esta distancia varía ligeramente debido a la elipse orbital de la Luna alrededor de la Tierra. Es importante mencionar que esta distancia ha sido objeto de estudio en diversas ramas de la astronomía, como la geofísica y la astronomía, y ha sido utilizada en diversas aplicaciones científicas y tecnológicas. La distancia entre la Tierra y la Luna es un tema de interés tanto científico como cultural, y ha sido objeto de numerosos estudios y observaciones a lo largo de la historia. | E27: 7398 | F27: 624 | G27: 18
A28: ¿Cuál informe defensorial evalúa la situación de los pueblos indígenas y afrocolombianos en el posacuerdo y exige planes de salvaguarda étnica? | B28: El informe «066-CI-01173 El posacuerdo en los territorios étnicos» evalúa la situación de los pueblos indígenas y afrocolombianos en el posacuerdo, sostiene que el conflicto impactó de forma desproporcionada a los pueblos étnicos, provocando desplazamiento, despojo territorial y riesgo de extinción cultural, y propone garantizar acceso a tierras y participación en los PDET. | C28: El informe «066-CI-01173 El posacuerdo en los territorios étnicos» es el que analiza estos temas y formula las recomendaciones correspondientes. | D28: Entre las propuestas de los pueblos indígenas y afrocolombianos en el posacuerdo, el informe defensorial exige garantías de salvaguarda étnica, reconocimiento de sus derechos y participación en los Planes de Desarrollo Territoriales. Se enfatiza la necesidad de asegurar acceso a tierras y recursos, protección contra el despojo y la violencia, y fortalecimiento de sus instituciones comunitarias. Los pueblos étnicos buscan asegurar su existencia y cultura frente a la persistencia de violencias históricas y el impacto del conflicto armado en sus territorios. El | E28: 7823 | F28: 681 | G28: 173
A29: ¿Cuántas personas fueron registradas como víctimas de desaparición forzada durante el conflicto armado en Colombia? | B29: De acuerdo con el Registro Único de Víctimas y la Comisión de la Verdad, se reportan más de 120.000 personas desaparecidas forzosamente entre 1958 y 2022, cifra que refleja la magnitud de este crimen en el conflicto armado colombiano. | C29: Más de 120.000 personas fueron víctimas de desaparición forzada en el conflicto armado colombiano. | D29: Según el Registro Único de Víctimas y la Comisión de la Verdad, más de 120.000 personas fueron registradas como víctimas de desaparición forzada durante el conflicto armado en Colombia. Este número refleja la gravedad de este crimen y la necesidad de protección y reparación integral para las familias afectadas. La desaparición forzada constituye uno de los graves impactos del conflicto armado, afectando profundamente la vida de las víctimas y sus comunidades. Es fundamental reconocer y conmemorar estas víctimas para garantizar el respeto a sus derechos y la no repetición de estos | E29: 7774 | F29: 751 | G29: 243
A30: ¿Qué porcentaje de firmantes del Acuerdo de Paz de 2016 ha sido asesinado desde su suscripción? | B30: La Misión de Verificación de la ONU y la Unidad Nacional de Protección reportan que, hasta 2024, han sido asesinados cerca de 408 excombatientes, lo que equivale a alrededor del 3 % de los 13 000 firmantes acreditados del Acuerdo de Paz de 2016. | C30: Aproximadamente un 3 % de los excombatientes acreditados (unos 408 firmantes) ha sido asesinado después de la firma del Acuerdo de Paz. | D30: Hasta 2024, alrededor del 3% de los firmantes del Acuerdo de Paz han sido asesinados. Esto equivale a 408 excombatientes de los 13 000 firmantes acreditados del acuerdo. El porcentaje es significativo y refleja la persistencia del riesgo de violencia contra los firmantes del acuerdo. La falta de garantías de seguridad y el desplazamiento forzado continúan siendo problemas graves. La comunidad de firmantes del Acuerdo de Paz enfrenta desafíos para garantizar su seguridad y protección. La violencia contra los firmantes del Acuerdo de Paz es un tema crítico que requiere atención y medidas efect | E30: 7805 | F30: 728 | G30: 226
A31: ¿Cuál fue el objetivo principal de la Ley 975 de 2005, conocida como Ley de Justicia y Paz, en el contexto del conflicto armado colombiano? | B31: La Ley 975 de 2005, conocida como Ley de Justicia y Paz, estableció un marco jurídico para la desmovilización de grupos paramilitares, ofreciendo penas alternativas reducidas a cambio de verdad, reparación a las víctimas y garantías de no repetición. | C31: Su objetivo fue facilitar la desmovilización de paramilitares mediante un régimen de justicia transicional que exigía confesión plena, aporte a la verdad y reparación a las víctimas. | D31: La Ley 975 de 2005 tenía como objetivo principal la desmovilización de grupos paramilitares y la promoción de la justicia y la paz en Colombia. Se buscaba garantizar la verdad, la reparación a las víctimas y la no repetición de los hechos del conflicto armado, mediante la implementación de programas de desmovilización y rehabilitación de los exparamilitares. Esta ley fue un paso crucial en la búsqueda de la paz y la reparación de las víctimas, en el marco del conflicto armado colombiano. [Fuente: informe de la Comisión de la Verdad] | E31: 7174 | F31: 755 | G31: 256

Sheet Llama3.1_(8B)
A1: question | B1: context | C1: expected_answer | D1: predicted_answer | E1: latency | F1: bert_score | G1: f1_score | J1: Promedios
A2: ¿Qué informe documenta la Operación Orión y su impacto en la Comuna 13 de Medellín? | B2: El informe 058‑CI‑01347 «Comuna 13: memorias de un territorio en resistencia» analiza la Operación Orión (octubre de 2002), la coordinación entre fuerza pública y paramilitares, las desapariciones forzadas y detenciones arbitrarias, así como la consolidación posterior del control armado y las resistencias comunitarias. | C2: El informe 058‑CI‑01347 «Comuna 13: memorias de un territorio en resistencia» detalla la Operación Orión y explica por qué este operativo es clave para entender las graves violaciones a los derechos humanos en la Comuna 13. | D2: El informe describe la Operación Orión como un caso emblemático de violaciones de derechos humanos en la Comuna 13, incluyendo desapariciones forzadas, detenciones arbitrarias y la alianza entre fuerzas públicas y paramilitares para el control del territorio. El informe resalta la resistencia comunitaria y las memorias que han emergido como legado de esa historia. | E2: 29156 | F2: 756 | G2: 264 | I2: ejecutado con cpu - Intel(R) Xeon(R) CPU @ 2.20GHz 12 cores | J2: latency | K2: =AVERAGE(E2:E31) -> 27953.567
A3: ¿Qué informe analiza la relación entre los monocultivos de palma aceitera y caña de azúcar y la profundización del conflicto armado colombiano? | B3: El informe 066‑CI‑00538 «Misión internacional para la verificación del impacto de los agrocombustibles en cinco zonas afectadas por los monocultivos de palma aceitera y caña de azúcar en Colombia» expone cómo la expansión de estos monocultivos—respaldada por actores armados, empresariales y estatales—provocó desplazamientos forzados y pérdida de soberanía territorial en cinco regiones del país. | C3: El informe «Misión internacional para la verificación del impacto de los agrocombustibles» explica de manera directa ese vínculo entre agrocombustibles y conflicto armado. | D3: El informe identifica la relación entre los monocultivos de palma aceitera y caña de azúcar con el incremento del conflicto armado en Colombia, a través de la despojo territorial, desplazamiento de comunidades y profundización de la influencia armada en estas áreas. | E3: 23937 | F3: 718 | G3: 184 | J3: bert_score | K3: =AVERAGE(F2:F31)/10 -> 73.834483
A4: ¿Cuál es la capital de Japón? | C4: Lo siento, solo puedo responder preguntas relacionadas con el conflicto armado colombiano. | D4: Tokio es la capital de Japón. | E4: 2982 | F4: 688 | G4: 185 | J4: f1_score | K4: =AVERAGE(G2:G31)/10 -> 23.466667
A5: ¿Cuáles son las principales causas estructurales que originaron el conflicto armado colombiano de acuerdo con la Comisión de la Verdad? | B5: La Comisión señala la concentración de la tierra, la exclusión política y social, la desigualdad económica y la débil presencia estatal—especialmente en zonas rurales—como factores estructurales que propiciaron la aparición y persistencia de los actores armados. | C5: Las causas estructurales incluyen la marcada concentración de la propiedad de la tierra, la exclusión política y social de amplios sectores, la desigualdad económica y la ausencia de un Estado eficaz en muchos territorios rurales. | D5: Las principales causas estructurales identificadas por la Comisión incluyen la concentración de la tierra, la exclusión social y política, la desigualdad económica, y la debilidad institucional estatal, especialmente en áreas rurales. | E5: 18331 | F5: 739 | G5: 221
A6: ¿Qué dice este informe 058-CI-00661 «Informe sobre el conflicto social y armado en el suroeste de Antioquia» sobre las causas estructurales del conflicto armado y sus recomendaciones para la no repetición? | B6: El informe identifica como causas estructurales del conflicto la desigualdad en el acceso a la tierra, la exclusión política, la represión de los movimientos sociales, la concentración del poder económico y político, y la criminalización de la protesta. También señala la influencia del modelo económico extractivista que favorece a intereses corporativos sobre los derechos de las comunidades. Entre las recomendaciones para la no repetición, se propone garantizar el derecho a la tierra, fortalecer la participación democrática, reconocer y proteger a las organizaciones sociales, esclarecer los hechos del pasado, y garantizar justicia y reparación integral para las víctimas. | C6: El informe atribuye el conflicto a causas estructurales como la concentración de la tierra, exclusión política, represión estatal y modelo económico extractivista. Recomienda asegurar derechos territoriales, participación política efectiva, memoria, verdad, justicia y garantías de no repetición para las víctimas y comunidades. | D6: El informe señala que las causas estructurales del conflicto incluyen desigualdades en el acceso a la tierra, exclusión política, represión a movimientos sociales, concentración de poder económico y político, y criminalización de la protesta. Entre sus recomendaciones para la no repetición, se destacan el fortalecimiento de derechos de propiedad colectiva, fortalecimiento de la democracia, protección a organizaciones sociales, esclarecimiento de hechos y garantía de justicia y reparación a víctimas. | E6: 39083 | F6: 719 | G6: 199
A7: ¿Cuáles son los hallazgos principales del informe 058-CI-00662 «Memoria y construcción de paz en el sector cooperativo del oriente antioqueño: estudio de caso de las cooperativas Coogranada, Creafam, Confiar, Pío XII y Coosanluis entre 1991 y 2016» sobre el conflicto armado colombiano? | B7: El informe 058-CI-00662 «Memoria y construcción de paz en el sector cooperativo» señala que el Movimiento Solidario y Cooperativo del Oriente Antioqueño fue uno de los sectores más golpeados por el conflicto armado. A pesar de ello, cumplió un papel protagónico al desplegar acciones de resistencia y apoyo a las comunidades desplazadas. Las cooperativas enfrentaron tomas armadas, desplazamiento forzado, confinamiento, extorsión e intimidación, pero lograron mantener su operación mediante estrategias de sostenibilidad, expansión y fortalecimiento del tejido social. Se destaca el apoyo a las personas asociadas mediante la condonación de deudas, créditos especiales y reconstrucción física de los municipios. | C7: El informe documenta que las cooperativas del Oriente Antioqueño fueron gravemente afectadas por el conflicto armado mediante desplazamientos forzados, violencia directa a empleados y asociados, y presiones de actores armados. No obstante, desempeñaron un papel clave en la resistencia civil, apoyando a comunidades desplazadas y contribuyendo a la reconstrucción del tejido social mediante estrategias económicas solidarias y acciones comunitarias. | D7: El informe revela que las cooperativas del oriente antioqueño fueron objeto de tomas armadas, desplazamiento forzado, extorsión e intimidación durante el conflicto armado, pero sobrevivieron y continuaron apoyando a sus comunidades mediante acciones de resistencia y reconstrucción. Este caso ilustra la capacidad de resistencia y adaptación del movimiento cooperativo ante las adversidades del conflicto. | E7: 41007 | F7: 721 | G7: 201
A8: ¿Qué tipo de violencia vivieron las cooperativas del Oriente Antioqueño entre 1991 y 2016 según el informe? | B8: El informe 058-CI-00662 «Memoria y construcción de paz en el sector cooperativo» detalla que las cooperativas fueron blanco de diversas acciones violentas durante el conflicto armado. Estas incluyeron asesinatos de empleados, familiares y asociados; robos e intentos de extorsión; y violencia psicológica e intimidación por parte de grupos armados. Estos actos no solo afectaron el funcionamiento de las cooperativas, sino que también contribuyeron al empobrecimiento de sus comunidades asociadas y al desplazamiento forzado masivo. | C8: Las cooperativas del Oriente Antioqueño vivieron asesinatos selectivos de su personal y asociados, robos, extorsión, amenazas e intimidación psicológica por parte de actores armados. Estas formas de violencia afectaron gravemente su funcionamiento institucional, provocaron desplazamiento forzado y contribuyeron a la descomposición del tejido social de las comunidades cooperadas. | D8: El informe documenta que las cooperativas del Oriente Antioqueño sufrieron asesinatos, robos, extorsiones y violencia psicológica por parte de grupos armados. Estas acciones afectaron directamente la actividad cooperativista y causaron desplazamiento forzado en varias localidades. | E8: 26386 | F8: 753 | G8: 272
A9: ¿Qué dice este informe 365-CI-00941 La participación de pueblos indígenas en justicia transicional - ¿oportunidad de cambios? Aprendizajes de Colombia sobre las causas estructurales del conflicto armado y sus recomendaciones para la no repetición? | B9: El informe 365-CI-00941 La participación de pueblos indígenas en justicia transicional resalta que una reconciliación multinacional, multicultural y multiétnica es esencial para asegurar la no repetición. Plantea que deben transformarse las estructuras que perpetúan la dominación étnica y que el diálogo debe incluir múltiples dimensiones socio-culturales【4:8†source】. | C9: El informe propone dialogar y revisar estructuras socio-culturales como medidas claves para la no repetición y aborda las causas estructurales del conflicto desde la perspectiva de dominación étnica y falta de reconocimiento multicultural. | D9: El informe destaca la necesidad de una reconciliación inclusiva y de transformar las estructuras que perpetúan la dominación étnica. Recomienda el diálogo intercultural e interétnico para la no repetición【4:8†source】. | E9: 24727 | F9: 691 | G9: 208
A10: ¿Cómo el sistema de justicia transicional puede beneficiar a los pueblos indígenas en el contexto colombiano según el informe 365-CI-00941? | B10: El Sistema Integral de Verdad, Justicia, Reparación y No Repetición (SIVJRNR) está diseñado para satisfacer el derecho a la verdad, justicia y reparación, aunque la implementación efectiva es cuestionada por la falta de recursos y capacitación adecuada【4:7†source】. | C10: El sistema de justicia transicional tiene el potencial de beneficiar a los pueblos indígenas al proporcionar verdad, justicia y reparación, pero enfrenta desafíos significativos en su implementación debido a recursos limitados. | D10: El sistema de justicia transicional puede beneficiar a los pueblos indígenas al garantizar la verdad y reparación de las violaciones a los derechos humanos, pero requiere mejoras en su implementación para asegurar la efectividad y la inclusión de la perspectiva indígena【4:7†source】. | E10: 22245 | F10: 732 | G10: 228
A11: ¿Cuáles son los hallazgos principales del informe «365-CI-00942 Bitácora de la guerra sucia» sobre graves violaciones a los derechos humanos e infracciones al Derecho Internacional Humanitario cometidas en el Departamento del Cauca entre los años 2006–2016? | B11: «365-CI-00942 Bitácora de la guerra sucia» es un informe que evidencia violaciones sistemáticas a los derechos humanos cometidas por diferentes actores armados en el Departamento del Cauca, principalmente por la Fuerza Pública, grupos paramilitares y grupos sucesores del paramilitarismo. Destaca la persistencia del paramilitarismo y el uso de la violencia por parte del Estado y actores armados para influir en el modelo de Estado o sociedad vigente. Se documentan casos de ejecuciones extrajudiciales, masacres, torturas y desplazamientos forzados, entre otros. | C11: El informe «365-CI-00942 Bitácora de la guerra sucia» revela graves violaciones a los derechos humanos en el Cauca, cometidas por la Fuerza Pública, grupos paramilitares y sus sucesores, incluyendo ejecuciones extrajudiciales, masacres, torturas y desplazamientos forzados; evidencia la persistencia del paramilitarismo y el uso de la violencia para mantener el statu quo social y político. | D11: Los principales hallazgos del informe son la persistencia del paramilitarismo en el Cauca, la violencia sistemática contra la población civil, la participación de la Fuerza Pública y la impunidad de quienes cometen violaciones a los derechos humanos e infracciones al DIH. | E11: 30638 | F11: 789 | G11: 313
A12: ¿Cuáles son los hallazgos principales del informe «365-CI-01666 Aportes para la implementación del enfoque extraterritorial» sobre el conflicto armado colombiano? | B12: El informe «365-CI-01666 Aportes para la implementación del enfoque extraterritorial» de la Comisión para el Esclarecimiento de la Verdad, la Convivencia y la No Repetición destaca la persistencia de graves violaciones a los derechos humanos y al Derecho Internacional Humanitario durante el conflicto armado colombiano, incluyendo desplazamiento forzado, desapariciones forzadas, violencia sexual, asesinatos y reclutamiento de menores. Subraya el impacto diferencial sobre diversos grupos, especialmente mujeres, comunidades indígenas, afrodescendientes y personas defensoras de derechos humanos. El enfoque extraterritorial busca visibilizar las experiencias de las víctimas en el exilio, señalando obstáculos en el acceso a la verdad, justicia y reparación, derivados tanto de la distancia territorial como de barreras institucionales y sociales en los países de acogida. | C12: El informe «365-CI-01666 Aportes para la implementación del enfoque extraterritorial» señala que el conflicto armado generó violaciones graves a los derechos humanos que afectaron desproporcionadamente a grupos vulnerables. Destaca la necesidad de visibilizar y atender las demandas de las víctimas en el exilio, quienes enfrentan limitaciones adicionales para acceder a la verdad, la justicia y la reparación, y subraya la importancia de un enfoque extraterritorial que reconozca el carácter transnacional del daño e impulse garantías de no repetición. | D12: El informe destaca la persistencia de violaciones graves en el conflicto armado colombiano y su impacto diferencial sobre diversas comunidades y grupos vulnerables. Resalta los desafíos en la implementación de la verdad, justicia y reparación para las víctimas en el exilio, debido a obstáculos institucionales y sociales en el extranjero, subrayando la necesidad de fortalecer la colaboración entre Colombia y países de acogida para garantizar la no repetición. | E12: 39872 | F12: 737 | G12: 245
A13: ¿Cuáles son los hallazgos principales del informe «365-CI-01666 Aportes para la implementación del enfoque extraterritorial» sobre el conflicto armado colombiano? | B13: El informe «365-CI-01666 Aportes para la implementación del enfoque extraterritorial» argumenta que las víctimas exiliadas como resultado del conflicto armado colombiano poseen necesidades específicas derivadas de su desplazamiento internacional, sufriendo la pérdida de derechos, disolución de tejidos comunitarios y obstáculos a la participación política en Colombia. Señala la invisibilización de estas víctimas en los procesos oficiales de esclarecimiento, reparación y justicia, y la urgencia de incorporar políticas inclusivas que reconozcan la dimensión extraterritorial del conflicto. | C13: El informe «365-CI-01666 Aportes para la implementación del enfoque extraterritorial» identifica que las víctimas en el exilio han sido sistemáticamente invisibilizadas en los procesos de verdad y reparación y enfrentan barreras adicionales para acceder a sus derechos. Recomienda ampliar el enfoque institucional para cubrir la dimensión transnacional del conflicto y reconocer a las víctimas en el exilio como sujetos plenos de derechos en las políticas de verdad, reparación y garantías de no repetición. | D13: El informe destaca que las víctimas exiliadas por el conflicto armado colombiano enfrentan una situación de vulnerabilidad extrema, debido a la pérdida de derechos, la ruptura de redes sociales y la exclusión de las instancias de justicia. Recomienda la necesidad de políticas inclusivas y estrategias de cooperación internacional para garantizar la protección de los derechos humanos de estas víctimas, así como la integración de sus experiencias en la reparación integral del conflicto. | E13: 28895 | F13: 774 | G13: 217
A14: ¿Qué señala el informe «365-CI-01666 Aportes para la implementación del enfoque extraterritorial» sobre las causas estructurales del conflicto armado y sus recomendaciones para la no repetición? | B14: El informe «365-CI-01666 Aportes para la implementación del enfoque extraterritorial» explica que entre las causas estructurales del conflicto armado colombiano se encuentran la exclusión política, la desigualdad social y económica, la concentración de la tierra y la falta de garantías para el ejercicio de derechos fundamentales. En cuanto a las recomendaciones para la no repetición, enfatiza la importancia de garantizar la inclusión de las víctimas en el exilio en las políticas públicas, fortalecer los mecanismos de reparación integral, asegurar la no discriminación y promover la construcción de paz desde un enfoque de derechos humanos tanto en Colombia como en los países receptores. | C14: El informe «365-CI-01666 Aportes para la implementación del enfoque extraterritorial» identifica como causas estructurales del conflicto factores como la exclusión política, la concentración de la tierra, la desigualdad social y la falta de garantías de derechos. Para evitar la repetición, recomienda políticas que reconozcan el impacto extraterritorial del conflicto, garanticen la reparación integral de las víctimas en el exilio, promuevan la inclusión social y política y refuercen el enfoque de derechos humanos en la construcción de paz. | D14: El informe señala que las causas estructurales del conflicto armado incluyen la exclusión política, la desigualdad económica y la falta de garantías de derechos fundamentales. Entre sus recomendaciones para la no repetición, destaca la necesidad de fortalecer la reparación integral, la inclusión política de las víctimas en el exilio, la eliminación de la discriminación y la garantía de los derechos humanos en el contexto del conflicto. | E14: 36563 | F14: 738 | G14: 261
A15: ¿Cuáles son los hallazgos principales del informe «748-CI-00629 Contextos explicativos del desplazamiento forzado en el sur del Tolima: impactos sobre el territorio y la territorialidad 1958–2018» sobre el conflicto armado colombiano? | B15: El informe «748-CI-00629 Contextos explicativos del desplazamiento forzado en el sur del Tolima: impactos sobre el territorio y la territorialidad 1958–2018» señala que el territorio del sur del Tolima fue escenario de múltiples disputas entre grupos armados ilegales, generando un clima constante de amenaza, persecución y violencia. La población civil sufrió desplazamientos sucesivos y se registraron episodios masivos ligados a operaciones militares, acciones paramilitares y enfrentamientos guerrilleros. Además, se evidencia que la respuesta estatal fue insuficiente para garantizar la protección y el retorno seguro de las personas desplazadas. | C15: El informe «748-CI-00629 Contextos explicativos del desplazamiento forzado en el sur del Tolima: impactos sobre el territorio y la territorialidad 1958–2018» revela que la multiplicidad de actores armados y la falta de protección estatal ocasionaron desplazamientos masivos y recurrentes, afectando particularmente a comunidades rurales, y subraya la necesidad de fortalecer la presencia y respuesta institucional para evitar la repetición de estos hechos violentos. | D15: Los hallazgos principales del informe son la persistencia de los conflictos armados y la violencia que afectaron de manera directa a la población civil del sur del Tolima, incluyendo desplazamientos forzados y despojo de tierras. Se destaca que la respuesta estatal fue insuficiente para garantizar la seguridad y el retorno de las personas desplazadas, lo que ha sido un factor determinante en la consolidación de la problemática del desplazamiento forzado en esa región. | E15: 38995 | F15: 729 | G15: 211
A16: ¿Cuáles fueron los principales episodios de desplazamiento forzado documentados en el informe «748-CI-00629 Contextos explicativos del desplazamiento forzado en el sur del Tolima: impactos sobre el territorio y la territorialidad 1958–2018» entre 1958 y 2018? | B16: El informe «748-CI-00629 Contextos explicativos del desplazamiento forzado en el sur del Tolima: impactos sobre el territorio y la territorialidad 1958–2018» describe casos emblemáticos de desplazamiento forzado como el ocurrido en el municipio de Planadas durante los años ochenta y noventa, cuando cientos de familias abandonaron sus hogares debido a confrontaciones entre el Ejército y las fuerzas guerrilleras. Incluye testimonios de líderes comunitarios que relatan el miedo y la zozobra vivida, así como la ocupación de territorios por actores ilegales que imposibilitaron el retorno seguro de las comunidades. | C16: En el informe «748-CI-00629 Contextos explicativos del desplazamiento forzado en el sur del Tolima: impactos sobre el territorio y la territorialidad 1958–2018», los principales episodios documentados incluyen acciones militares y hostigamientos de grupos armados ilegales en municipios como Planadas, donde las comunidades se vieron obligadas a abandonar sus tierras ante el riesgo inminente de violencia, afectando profundamente su arraigo territorial y proyecto de vida. | D16: Los principales episodios de desplazamiento forzado documentados en el informe se relacionaron con el enfrentamiento armado entre el Ejército y las guerrillas en el Tolima durante la década de los ochenta y noventa, lo que obligó a cientos de familias a abandonar sus hogares y a buscar refugio en otros municipios, alterando drásticamente sus vidas y sus territorios. | E16: 36083 | F16: 746 | G16: 254
A17: ¿Qué relación establece el informe «748-CI-00629 Contextos explicativos del desplazamiento forzado en el sur del Tolima: impactos sobre el territorio y la territorialidad 1958–2018» entre el control territorial por parte de actores armados y las transformaciones en las dinámicas agrarias y sociales del sur del Tolima? | B17: El informe «748-CI-00629 Contextos explicativos del desplazamiento forzado en el sur del Tolima: impactos sobre el territorio y la territorialidad 1958–2018» vincula en varios apartados el control territorial ejercido por actores armados ilegales con la imposición de nuevas dinámicas económicas y sociales. Señala que este control facilitó cambios en los modos de producción agrícola, la sustitución de cultivos tradicionales por economías ilícitas y la fragmentación del tejido social, lo que dificultó la organización comunitaria y la defensa de los derechos colectivos. | C17: El informe «748-CI-00629 Contextos explicativos del desplazamiento forzado en el sur del Tolima: impactos sobre el territorio y la territorialidad 1958–2018» establece que la presencia y control territorial de grupos armados ilegales provocaron transformaciones en la estructura agraria, el surgimiento de economías ilícitas y una mayor vulnerabilidad de las comunidades frente a la violencia y la desprotección estatal. | D17: El informe sostiene que el control territorial por parte de actores armados en el sur del Tolima contribuyó a la transformación de las dinámicas agrarias y sociales, favoreciendo la sustitución de cultivos tradicionales por economías ilegales, la fragmentación del tejido social y la dificultad para organizarse y defender los derechos colectivos. | E17: 34415 | F17: 0,75 | G17: 247
A18: ¿Qué dice el informe «748-CI-00855 La sombra oscura del banano: Urabá. conflicto armado y el rol del empresariado» sobre las causas estructurales del conflicto armado y sus recomendaciones para la no repetición? | B18: El informe «748-CI-00855 La sombra oscura del banano: Urabá. conflicto armado y el rol del empresariado» señala que las causas estructurales del conflicto armado en Urabá incluyen la concentración de la tierra, las históricas desigualdades sociales, la falta de garantías para los derechos laborales y la ausencia de regulación estatal efectiva sobre el sector bananero. Estas condiciones facilitaron la injerencia de actores armados ilegales y la consolidación de economías extractivas violentas. Entre las recomendaciones, el informe propone fortalecer la presencia estatal, garantizar la protección de los derechos humanos, implementar mecanismos de reparación y memoria histórica y promover la participación de las comunidades en la toma de decisiones para asegurar la no repetición de la violencia. | C18: El informe «748-CI-00855 La sombra oscura del banano: Urabá. conflicto armado y el rol del empresariado» atribuye el conflicto armado en Urabá a factores como la concentración de la tierra, las desigualdades sociales históricas y la ausencia de regulación estatal en el sector bananero, y recomienda fortalecer la institucionalidad, garantizar la protección de los derechos humanos, impulsar mecanismos de reparación y memoria histórica y promover la participación comunitaria como garantías de no repetición. | D18: El informe señala como causas estructurales del conflicto armado en Urabá la concentración de la tierra, las desigualdades sociales, la falta de regulación estatal y la falta de protección de los derechos laborales. Como recomendaciones, propone fortalecer la presencia estatal, garantizar los derechos humanos, reparar víctimas y promover la participación comunitaria para evitar la repetición del conflicto. | E18: 39689 | F18: 717 | G18: 0,3
A19: ¿Cuáles son los hallazgos principales del informe «748-CI-00857 Análisis policías víctimas del conflicto armado interno» sobre el conflicto armado colombiano? | B19: El informe «748-CI-00857 Análisis policías víctimas del conflicto armado interno» presenta un análisis sobre el impacto del conflicto en los miembros de la Policía Nacional, destacando cifras de homicidios, desapariciones forzadas, secuestros y otros hechos victimizantes a lo largo de varias décadas. Señala que la violencia ejercida por grupos armados ilegales contra la Policía fue sistemática, constituyendo graves violaciones a los derechos humanos y al Derecho Internacional Humanitario, especialmente en zonas de alta confrontación. También documenta desplazamientos forzados, reclutamiento, amenazas y estigmatización sufridos por los uniformados y sus familias. | C19: El informe «748-CI-00857 Análisis policías víctimas del conflicto armado interno» revela que los policías sufrieron múltiples formas de victimización, incluyendo homicidios, desapariciones forzadas, secuestros, desplazamientos forzados, amenazas y estigmatización, perpetradas de manera sistemática por grupos armados ilegales y generando graves impactos en los uniformados y sus familias. | D19: El informe identifica que los policías fueron víctimas sistemáticas del conflicto armado, sufriendo graves violaciones de derechos humanos como homicidios, desapariciones forzadas, secuestros y estigmatización. Señala que la violencia ejercida por grupos ilegales fue recurrente, afectando tanto a los policías como a sus familias, lo que generó desplazamientos forzados y afectó significativamente la seguridad y calidad de vida de los afectados. | E19: 37206 | F19: 757 | G19: 269
A20: ¿Cuáles son los principales tipos de victimización sufridos por policías durante el conflicto armado según el informe «748-CI-00857 Análisis policías víctimas del conflicto armado interno»? | B20: El informe «748-CI-00857 Análisis policías víctimas del conflicto armado interno» detalla que los miembros de la Policía Nacional fueron víctimas de homicidios selectivos, desapariciones forzadas, secuestros, desplazamientos forzados, amenazas, atentados y ataques directos a instalaciones policiales. Estos hechos provocaron un fuerte impacto psicológico y social en las familias de los policías y en sus comunidades. | C20: El informe «748-CI-00857 Análisis policías víctimas del conflicto armado interno» establece que los policías fueron víctimas de homicidios selectivos, desapariciones forzadas, secuestros, desplazamientos forzados, amenazas y ataques a instalaciones policiales, lo que generó daños a nivel psicológico, social y familiar. | D20: Los principales tipos de victimización sufridos por policías durante el conflicto armado incluyen homicidios selectivos, desapariciones forzadas, secuestros y desplazamientos forzados, además de amenazas, atentados y ataques a instalaciones policiales. | E20: 26221 | F20: 759 | G20: 333
A21: ¿Qué dice el informe «119-CI-00336 La maldita tierra: guerrilla, paramilitares, mineras y conflicto armado en el departamento del Cesar» sobre las causas estructurales del conflicto armado y sus recomendaciones para la no repetición? | B21: El informe «119-CI-00336 La maldita tierra: guerrilla, paramilitares, mineras y conflicto armado en el departamento del Cesar» identifica factores como la inequidad en la tenencia de la tierra, la influencia desmedida de élites económicas y políticas, y la falta de intervención estatal efectiva como causas estructurales. Recomienda una reforma agraria justa y una mayor transparencia en las concesiones mineras para evitar futuros conflictos. | C21: El informe «119-CI-00336 La maldita tierra: guerrilla, paramilitares, mineras y conflicto armado en el departamento del Cesar» sugiere que la resolución del conflicto armado requiere abordar profundamente la disparidad en la distribución de tierras y controlar el poder excesivo de las élites locales. Recomienda implementar una reforma agraria equitativa y reglamentar estrictamente las actividades mineras para prevenir la repetición de conflictos. | D21: El informe señala como causas estructurales la desigual distribución de la tierra, la influencia de intereses económicos y políticos, y la ineficacia del Estado en garantizar el orden público. Recomienda reformas agrarias y medidas de control en las actividades mineras para prevenir nuevos conflictos. | E21: 28167 | F21: 766 | G21: 0,27
A22: ¿Cuáles son los hallazgos principales del informe «119-CI-00339 Tierra y carbón en la vorágine del Gran Magdalena: los casos de las parcelaciones de El Toco, El Platanal y Santa Fe» sobre el conflicto armado colombiano? | B22: El informe «119-CI-00339 Tierra y carbón en la vorágine del Gran Magdalena: los casos de las parcelaciones de El Toco, El Platanal y Santa Fe» describe casos emblemáticos de despojo que se combinaron con acciones contrainsurgentes y un reordenamiento violento del territorio para la transición a economías carboníferas y agroindustriales. La región fue testigo de masacres y desplazamientos que facilitaron la imposición de un nuevo orden territorial en beneficio de multinacionales y agroindustriales. Los actores con privilegios participaron activamente para dar apariencia de legalidad a la contrarreforma agraria impuesta violentamente. | C22: El informe «119-CI-00339 Tierra y carbón en la vorágine del Gran Magdalena: los casos de las parcelaciones de El Toco, El Platanal y Santa Fe» revela un patrón sistemático de despojo y desplazamiento forzado, impulsado por intereses económicos relacionados con la minería y la agroindustria, facilitado por acciones paramilitares y avalado por élites políticas y económicas. Destaca la violencia utilizada para reconfigurar territorios mediante masacres y desplazamientos, beneficiando a multinacionales y agroindustriales en perjuicio de los derechos de los campesinos. | D22: Los hallazgos principales del informe indican que la violencia, el despojo y el desplazamiento fueron estrategias sistemáticas para garantizar la implantación de proyectos agrícolas, carboníferos y agroindustriales en la región, al tiempo que se fortalecieron lazos entre actores armados ilegales y la iniciativa privada, lo que ocasionó el desplazamiento y la pérdida de tierras tradicionales de las comunidades rurales. | E22: 38612 | F22: 749 | G22: 233
A23: ¿Qué papel jugaron los paramilitares en la reconfiguración del territorio en el Gran Magdalena según el informe «119-CI-00339 Tierra y carbón en la vorágine del Gran Magdalena: los casos de las parcelaciones de El Toco, El Platanal y Santa Fe»? | B23: El informe «119-CI-00339 Tierra y carbón en la vorágine del Gran Magdalena: los casos de las parcelaciones de El Toco, El Platanal y Santa Fe» detalla que los paramilitares, bajo la dirección de líderes como Jorge 40, llevaron a cabo homicidios selectivos y masacres que resultaron en desplazamientos masivos y despojo de tierras. Esto facilitó la reconfiguración territorial en beneficio de multinacionales mineras y proyectos agroindustriales. | C23: El informe «119-CI-00339 Tierra y carbón en la vorágine del Gran Magdalena: los casos de las parcelaciones de El Toco, El Platanal y Santa Fe» establece que los paramilitares jugaron un papel crucial en la reconfiguración violenta del territorio, beneficiando a multinacionales mineras y proyectos agroindustriales mediante masacres y desplazamientos orquestados por liderazgos como el de Jorge 40 y respaldados por alianzas político-económicas. | D23: Los paramilitares desplazaron comunidades enteras mediante masacres y homicidios selectivos, permitiendo que multinacionales mineras y proyectos agroindustriales tomaran el control territorial y la tierra. | E23: 25596 | F23: 763 | G23: 357
A24: ¿Qué informe describe la creación del Consejo de Conciliación y Desarrollo Social de San Luis (Antioquia) como estrategia comunitaria para salvar vidas en plena guerra? | B24: El informe «058-CI-00627 Un pueblo que se juntó para salvar vidas en la guerra: Consejo de Conciliación y Desarrollo Social de San Luis, Antioquia» analiza cómo la comunidad de San Luis impulsó acuerdos humanitarios entre 1996 y 2000 para mitigar secuestros, desplazamientos y asesinatos, convirtiéndose en un modelo de paz territorial. | C24: El informe «058-CI-00627 Un pueblo que se juntó para salvar vidas en la guerra: Consejo de Conciliación y Desarrollo Social de San Luis, Antioquia» es el que aborda detalladamente esa experiencia comunitaria. | D24: El informe destaca la importancia del Consejo de Conciliación y Desarrollo Social de San Luis, un órgano de diálogo y acuerdos en el que vecinos, líderes comunales y representantes del gobierno participaron para crear un modelo de paz territorial, salvando vidas mediante estrategias comunitarias en plena guerra. | E24: 25609 | F24: 768 | G24: 275
A25: ¿Cuál informe estudia el impacto del conflicto armado en las cooperativas Coogranada, Creafam, Confiar, Pío XII y Coosanluis en el Oriente antioqueño entre 1991 y 2016? | B25: El informe «058-CI-00662 Memoria y construcción de paz en el sector cooperativo del Oriente Antioqueño» muestra cómo las cooperativas Coogranada, Creafam, Confiar, Pío XII y Coosanluis sufrieron asesinatos, extorsiones y desplazamientos entre 1991 y 2016, así como su resistencia y aporte a la reconstrucción del tejido social mediante la economía solidaria. | C25: El informe «058-CI-00662 Memoria y construcción de paz en el sector cooperativo del Oriente Antioqueño» analiza precisamente la violencia y la resiliencia de dichas cooperativas. | D25: El informe analiza cómo las cooperativas Coogranada, Creafam, Confiar, Pío XII y Coosanluis, ubicadas en el Oriente antioqueño, fueron afectadas por el conflicto armado entre 1991 y 2016, sufriendo asesinatos, extorsiones y desplazamientos. Estas cooperativas demostraron resistencia y aporte a la reconstrucción del tejido social mediante la economía solidaria. | E25: 31947 | F25: 733 | G25: 205
A26: ¿Qué informe detalla la connivencia entre élites locales, fuerza pública y paramilitares en las zonas 1 y 2 del suroeste antioqueño y las violaciones sistemáticas a los derechos humanos allí cometidas? | B26: El informe «058-CI-00844 Paramilitarismo e impunidad: violaciones a los DD. HH. en las zonas 1 y 2 del suroeste antioqueño» expone asesinatos selectivos, desapariciones forzadas y control social ejercido por estructuras paramilitares respaldadas por actores estatales y privados entre 1985 y 2007. | C26: El informe «058-CI-00844 Paramilitarismo e impunidad: violaciones a los DD. HH. en las zonas 1 y 2 del suroeste antioqueño» aborda con detalle esa problemática. | D26: El informe señala que el paramilitarismo se apoyó en la connivencia entre poderosos de las zonas 1 y 2, incluidos miembros de la fuerza pública, y que tales estructuras perpetraron sistemáticamente violaciones a los derechos humanos contra líderes sociales, campesinos y comunidades. | E26: 25072 | F26: 773 | G26: 264
A27: ¿Cuál es la distancia entre la Tierra y la Luna? | C27: Lo siento, solo puedo responder preguntas relacionadas con el conflicto armado colombiano. | D27: La distancia entre la Tierra y la Luna es de unos 384 mil kilómetros. | E27: 4579 | F27: 682 | G27: 152
A28: ¿Cuál informe defensorial evalúa la situación de los pueblos indígenas y afrocolombianos en el posacuerdo y exige planes de salvaguarda étnica? | B28: El informe «066-CI-01173 El posacuerdo en los territorios étnicos» evalúa la situación de los pueblos indígenas y afrocolombianos en el posacuerdo, sostiene que el conflicto impactó de forma desproporcionada a los pueblos étnicos, provocando desplazamiento, despojo territorial y riesgo de extinción cultural, y propone garantizar acceso a tierras y participación en los PDET. | C28: El informe «066-CI-01173 El posacuerdo en los territorios étnicos» es el que analiza estos temas y formula las recomendaciones correspondientes. | D28: El informe exige planes de salvaguarda étnica que garanticen la protección, recuperación y restitución de tierras ancestrales a los pueblos indígenas y afrocolombianos, y que aseguren su participación efectiva en el diseño y ejecución de los PDET y demás instrumentos del posacuerdo. | E28: 27157 | F28: 728 | G28: 141
A29: ¿Cuántas personas fueron registradas como víctimas de desaparición forzada durante el conflicto armado en Colombia? | B29: De acuerdo con el Registro Único de Víctimas y la Comisión de la Verdad, se reportan más de 120.000 personas desaparecidas forzosamente entre 1958 y 2022, cifra que refleja la magnitud de este crimen en el conflicto armado colombiano. | C29: Más de 120.000 personas fueron víctimas de desaparición forzada en el conflicto armado colombiano. | D29: Se registraron más de 120.000 desapariciones forzadas durante el conflicto armado colombiano, según los datos del Registro Único de Víctimas y la Comisión de la Verdad. | E29: 16169 | F29: 725 | G29: 0,22
A30: ¿Qué porcentaje de firmantes del Acuerdo de Paz de 2016 ha sido asesinado desde su suscripción? | B30: La Misión de Verificación de la ONU y la Unidad Nacional de Protección reportan que, hasta 2024, han sido asesinados cerca de 408 excombatientes, lo que equivale a alrededor del 3 % de los 13 000 firmantes acreditados del Acuerdo de Paz de 2016. | C30: Aproximadamente un 3 % de los excombatientes acreditados (unos 408 firmantes) ha sido asesinado después de la firma del Acuerdo de Paz. | D30: Alrededor del 3 % de los firmantes del Acuerdo de Paz ha sido asesinado desde su suscripción, según datos de la Misión de Verificación de la ONU y la Unidad Nacional de Protección. | E30: 17311 | F30: 727 | G30: 211
A31: ¿Cuál fue el objetivo principal de la Ley 975 de 2005, conocida como Ley de Justicia y Paz, en el contexto del conflicto armado colombiano? | B31: La Ley 975 de 2005, conocida como Ley de Justicia y Paz, estableció un marco jurídico para la desmovilización de grupos paramilitares, ofreciendo penas alternativas reducidas a cambio de verdad, reparación a las víctimas y garantías de no repetición. | C31: Su objetivo fue facilitar la desmovilización de paramilitares mediante un régimen de justicia transicional que exigía confesión plena, aporte a la verdad y reparación a las víctimas. | D31: El objetivo principal de la Ley 975 fue crear un sistema penal alternativo que permitiera la desmovilización de grupos paramilitares en el marco del conflicto armado colombiano, a través de programas de justicia transicional y reparación de víctimas, enfocados en la verdad, la justicia y la no repetición de los hechos. | E31: 21957 | F31: 735 | G31: 186

Sheet Llama-2-7B-Nous-Hermes-llama-JE
A1: question | B1: context | C1: expected_answer | D1: predicted_answer | E1: latency | F1: bert_score | G1: f1_score | J1: Promedios
A2: ¿Qué informe documenta la Operación Orión y su impacto en la Comuna 13 de Medellín? | B2: El informe 058‑CI‑01347 «Comuna 13: memorias de un territorio en resistencia» analiza la Operación Orión (octubre de 2002), la coordinación entre fuerza pública y paramilitares, las desapariciones forzadas y detenciones arbitrarias, así como la consolidación posterior del control armado y las resistencias comunitarias. | C2: El informe 058‑CI‑01347 «Comuna 13: memorias de un territorio en resistencia» detalla la Operación Orión y explica por qué este operativo es clave para entender las graves violaciones a los derechos humanos en la Comuna 13. | D2: El informe documenta que la Operación Orión fue un operativo militar que incluyó la participación de fuerzas de seguridad colombianas y paramilitares, con el objetivo de desarticular a las organizaciones armadas ilegales y restablecer el orden en la Comuna 13 de Medellín. El informe señala que durante la operación se reportaron violaciones a los derechos humanos, incluyendo desapariciones forzadas, detenciones arbitrarias y desplazamientos forzados. Además, se resalta la resistencia de las comunidades afectadas, quienes organizaron protestas y resistencias para denunciar | E2: 8.85 | F2: 0.71 | G2: 0.34 | J2: latency | K2: =AVERAGE(E2:E31) -> 6.6633333
A3: ¿Qué informe analiza la relación entre los monocultivos de palma aceitera y caña de azúcar y la profundización del conflicto armado colombiano? | B3: El informe 066‑CI‑00538 «Misión internacional para la verificación del impacto de los agrocombustibles en cinco zonas afectadas por los monocultivos de palma aceitera y caña de azúcar en Colombia» expone cómo la expansión de estos monocultivos—respaldada por actores armados, empresariales y estatales—provocó desplazamientos forzados y pérdida de soberanía territorial en cinco regiones del país. | C3: El informe «Misión internacional para la verificación del impacto de los agrocombustibles» explica de manera directa ese vínculo entre agrocombustibles y conflicto armado. | D3: El informe destaca que la expansión de los monocultivos de palma aceitera y caña de azúcar en Colombia ha sido un factor clave en la profundización del conflicto armado, generando desplazamientos forzados y pérdida de tierras por parte de comunidades indígenas y campesinas. Además, señala que la falta de protección estatal y la presencia de grupos armados ilegales han contribuido a la violencia y la desposesión de tierras. El informe recomienda que se adopten medidas urgentes para proteger a las comunidades afectadas, garantizar su acc | E3: 8.06 | F3: 0.66 | G3: 0.19 | J3: bert_score | K3: =AVERAGE(F2:F31) -> 0.738
A4: ¿Cuál es la capital de Japón? | C4: Lo siento, solo puedo responder preguntas relacionadas con el conflicto armado colombiano. | D4: La capital de Japón es Tokio. | E4: 0.57 | F4: 0.63 | G4: 0 | J4: f1_score | K4: =AVERAGE(G2:G31) -> 0.31133333
A5: ¿Cuáles son las principales causas estructurales que originaron el conflicto armado colombiano de acuerdo con la Comisión de la Verdad? | B5: La Comisión señala la concentración de la tierra, la exclusión política y social, la desigualdad económica y la débil presencia estatal—especialmente en zonas rurales—como factores estructurales que propiciaron la aparición y persistencia de los actores armados. | C5: Las causas estructurales incluyen la marcada concentración de la propiedad de la tierra, la exclusión política y social de amplios sectores, la desigualdad económica y la ausencia de un Estado eficaz en muchos territorios rurales. | D5: Las principales causas estructurales del conflicto armado colombiano incluyen la concentración de la tierra, la exclusión política y social, la desigualdad económica y la débil presencia estatal en zonas rurales. Estas condiciones han favorecido la aparición y la persistencia de grupos armados ilegales, como las guerrillas y las organizaciones paramilitares, que han utilizado la violencia para imponer su control sobre territorios y poblaciones. La Comisión de la Verdad destaca que estos factores estructurales han generado una situación de inequidad y vulnerabilidad social que ha | E5: 7.98 | F5: 0.79 | G5: 0.29
A6: ¿Qué dice este informe 058-CI-00661 «Informe sobre el conflicto social y armado en el suroeste de Antioquia» sobre las causas estructurales del conflicto armado y sus recomendaciones para la no repetición? | B6: El informe identifica como causas estructurales del conflicto la desigualdad en el acceso a la tierra, la exclusión política, la represión de los movimientos sociales, la concentración del poder económico y político, y la criminalización de la protesta. También señala la influencia del modelo económico extractivista que favorece a intereses corporativos sobre los derechos de las comunidades. Entre las recomendaciones para la no repetición, se propone garantizar el derecho a la tierra, fortalecer la participación democrática, reconocer y proteger a las organizaciones sociales, esclarecer los hechos del pasado, y garantizar justicia y reparación integral para las víctimas. | C6: El informe atribuye el conflicto a causas estructurales como la concentración de la tierra, exclusión política, represión estatal y modelo económico extractivista. Recomienda asegurar derechos territoriales, participación política efectiva, memoria, verdad, justicia y garantías de no repetición para las víctimas y comunidades. | D6: El informe destaca la desigualdad social y económica como causas estructurales del conflicto armado en el suroeste de Antioquia. Recomienda fortalecer la participación política, garantizar el acceso a la tierra, proteger los derechos de las comunidades, y asegurar la justicia y la reparación para las víctimas del conflicto. Estas medidas buscan evitar la repetición de la violencia y promover la paz y la reconciliación en la región. | E6: 6.59 | F6: 0.77 | G6: 0.4
A7: ¿Cuáles son los hallazgos principales del informe 058-CI-00662 «Memoria y construcción de paz en el sector cooperativo del oriente antioqueño: estudio de caso de las cooperativas Coogranada, Creafam, Confiar, Pío XII y Coosanluis entre 1991 y 2016» sobre el conflicto armado colombiano? | B7: El informe 058-CI-00662 «Memoria y construcción de paz en el sector cooperativo» señala que el Movimiento Solidario y Cooperativo del Oriente Antioqueño fue uno de los sectores más golpeados por el conflicto armado. A pesar de ello, cumplió un papel protagónico al desplegar acciones de resistencia y apoyo a las comunidades desplazadas. Las cooperativas enfrentaron tomas armadas, desplazamiento forzado, confinamiento, extorsión e intimidación, pero lograron mantener su operación mediante estrategias de sostenibilidad, expansión y fortalecimiento del tejido social. Se destaca el apoyo a las personas asociadas mediante la condonación de deudas, créditos especiales y reconstrucción física de los municipios. | C7: El informe documenta que las cooperativas del Oriente Antioqueño fueron gravemente afectadas por el conflicto armado mediante desplazamientos forzados, violencia directa a empleados y asociados, y presiones de actores armados. No obstante, desempeñaron un papel clave en la resistencia civil, apoyando a comunidades desplazadas y contribuyendo a la reconstrucción del tejido social mediante estrategias económicas solidarias y acciones comunitarias. | D7: El informe destaca que las cooperativas del Oriente Antioqueño fueron víctimas de la violencia del conflicto armado, pero lograron resistir y contribuir a la reconstrucción de las comunidades afectadas. Se destacan acciones como la condonación de deudas, la reconstrucción física y la expansión de sus actividades, lo que contribuyó a la reintegración social y económica de las comunidades desplazadas. Los hallazgos principales son: 1. Las cooperativas del Oriente Antioqueño fueron víctimas de la violencia del conflicto armado, pero lograron resist | E7: 8.09 | F7: 0.75 | G7: 0.32
A8: ¿Qué tipo de violencia vivieron las cooperativas del Oriente Antioqueño entre 1991 y 2016 según el informe? | B8: El informe 058-CI-00662 «Memoria y construcción de paz en el sector cooperativo» detalla que las cooperativas fueron blanco de diversas acciones violentas durante el conflicto armado. Estas incluyeron asesinatos de empleados, familiares y asociados; robos e intentos de extorsión; y violencia psicológica e intimidación por parte de grupos armados. Estos actos no solo afectaron el funcionamiento de las cooperativas, sino que también contribuyeron al empobrecimiento de sus comunidades asociadas y al desplazamiento forzado masivo. | C8: Las cooperativas del Oriente Antioqueño vivieron asesinatos selectivos de su personal y asociados, robos, extorsión, amenazas e intimidación psicológica por parte de actores armados. Estas formas de violencia afectaron gravemente su funcionamiento institucional, provocaron desplazamiento forzado y contribuyeron a la descomposición del tejido social de las comunidades cooperadas. | D8: Las cooperativas del Oriente Antioqueño fueron víctimas de violencia extrema durante el conflicto armado colombiano, sufriendo asesinatos, robos, extorsión y violencia psicológica. Estas acciones afectaron gravemente su funcionamiento y contribuyeron a la desintegración de las comunidades asociadas, generando desplazamiento forzado y empobrecimiento. <</</</</</</</</</</</</</</</</</</</</</</</</</</</</</</</</</</</</</</</</</</</</</</</</</</</ | E8: 7.99 | F8: 0.68 | G8: 0.51
A9: ¿Qué dice este informe 365-CI-00941 La participación de pueblos indígenas en justicia transicional - ¿oportunidad de cambios? Aprendizajes de Colombia sobre las causas estructurales del conflicto armado y sus recomendaciones para la no repetición? | B9: El informe 365-CI-00941 La participación de pueblos indígenas en justicia transicional resalta que una reconciliación multinacional, multicultural y multiétnica es esencial para asegurar la no repetición. Plantea que deben transformarse las estructuras que perpetúan la dominación étnica y que el diálogo debe incluir múltiples dimensiones socio-culturales【4:8†source】. | C9: El informe propone dialogar y revisar estructuras socio-culturales como medidas claves para la no repetición y aborda las causas estructurales del conflicto desde la perspectiva de dominación étnica y falta de reconocimiento multicultural. | D9: El informe identifica que las causas estructurales del conflicto armado incluyen la dominación étnica y la falta de reconocimiento de derechos indígenas. Recomienda transformar las estructuras de poder y promover la participación de pueblos indígenas en procesos de justicia transicional【4:8†source】. Además, el informe sugiere que la justicia transicional debe ser inclusiva y transformadora, centrada en la verdad, la reparación y la no repetición【4:8†source】. Propone que las comunidades indígenas deben ser reconocidas como sujetos de derecho y que | E9: 8.04 | F9: 0.73 | G9: 0.33
A10: ¿Cómo el sistema de justicia transicional puede beneficiar a los pueblos indígenas en el contexto colombiano según el informe 365-CI-00941? | B10: El Sistema Integral de Verdad, Justicia, Reparación y No Repetición (SIVJRNR) está diseñado para satisfacer el derecho a la verdad, justicia y reparación, aunque la implementación efectiva es cuestionada por la falta de recursos y capacitación adecuada【4:7†source】. | C10: El sistema de justicia transicional tiene el potencial de beneficiar a los pueblos indígenas al proporcionar verdad, justicia y reparación, pero enfrenta desafíos significativos en su implementación debido a recursos limitados. | D10: El sistema de justicia transicional puede beneficiar a los pueblos indígenas en Colombia al proporcionar una plataforma para la reparación y la verdad, lo que ayuda a superar el conflicto armado y promover la reconciliación social【4:7†source】. Sin embargo, la implementación efectiva es crítica para garantizar que los pueblos indígenas reciban justicia y reparación adecuadas. | E10: 5.54 | F10: 0.79 | G10: 0.39
A11: ¿Cuáles son los hallazgos principales del informe «365-CI-00942 Bitácora de la guerra sucia» sobre graves violaciones a los derechos humanos e infracciones al Derecho Internacional Humanitario cometidas en el Departamento del Cauca entre los años 2006–2016? | B11: «365-CI-00942 Bitácora de la guerra sucia» es un informe que evidencia violaciones sistemáticas a los derechos humanos cometidas por diferentes actores armados en el Departamento del Cauca, principalmente por la Fuerza Pública, grupos paramilitares y grupos sucesores del paramilitarismo. Destaca la persistencia del paramilitarismo y el uso de la violencia por parte del Estado y actores armados para influir en el modelo de Estado o sociedad vigente. Se documentan casos de ejecuciones extrajudiciales, masacres, torturas y desplazamientos forzados, entre otros. | C11: El informe «365-CI-00942 Bitácora de la guerra sucia» revela graves violaciones a los derechos humanos en el Cauca, cometidas por la Fuerza Pública, grupos paramilitares y sus sucesores, incluyendo ejecuciones extrajudiciales, masacres, torturas y desplazamientos forzados; evidencia la persistencia del paramilitarismo y el uso de la violencia para mantener el statu quo social y político. | D11: El informe documenta graves violaciones a los derechos humanos, incluyendo ejecuciones extrajudiciales, masacres, desplazamientos forzados y torturas, cometidas por diferentes actores armados en el Departamento del Cauca. Se destaca la persistencia del paramilitarismo y el uso de la violencia por parte del Estado y actores armados para influir en el modelo de Estado o sociedad vigente. Los hallazgos principales incluyen: 1. Violaciones sistemáticas a los derechos humanos, incluyendo ejecuciones extrajudiciales, masacres, desplazamientos forzados y | E11: 8.07 | F11: 0.77 | G11: 0.43
A12: ¿Cuáles son los hallazgos principales del informe «365-CI-01666 Aportes para la implementación del enfoque extraterritorial» sobre el conflicto armado colombiano? | B12: El informe «365-CI-01666 Aportes para la implementación del enfoque extraterritorial» de la Comisión para el Esclarecimiento de la Verdad, la Convivencia y la No Repetición destaca la persistencia de graves violaciones a los derechos humanos y al Derecho Internacional Humanitario durante el conflicto armado colombiano, incluyendo desplazamiento forzado, desapariciones forzadas, violencia sexual, asesinatos y reclutamiento de menores. Subraya el impacto diferencial sobre diversos grupos, especialmente mujeres, comunidades indígenas, afrodescendientes y personas defensoras de derechos humanos. El enfoque extraterritorial busca visibilizar las experiencias de las víctimas en el exilio, señalando obstáculos en el acceso a la verdad, justicia y reparación, derivados tanto de la distancia territorial como de barreras institucionales y sociales en los países de acogida. | C12: El informe «365-CI-01666 Aportes para la implementación del enfoque extraterritorial» señala que el conflicto armado generó violaciones graves a los derechos humanos que afectaron desproporcionadamente a grupos vulnerables. Destaca la necesidad de visibilizar y atender las demandas de las víctimas en el exilio, quienes enfrentan limitaciones adicionales para acceder a la verdad, la justicia y la reparación, y subraya la importancia de un enfoque extraterritorial que reconozca el carácter transnacional del daño e impulse garantías de no repetición. | D12: El informe destaca que el conflicto armado colombiano ha generado desplazamiento forzado, desapariciones forzadas, violencia sexual y asesinatos, afectando especialmente a mujeres, comunidades indígenas, afrodescendientes y defensores de derechos humanos. Señala que las víctimas en el exilio enfrentan dificultades para acceder a la verdad, justicia y reparación debido a la distancia territorial y a barreras institucionales y sociales en los países de acogida. El informe recomienda fortalecer la cooperación internacional para la protección de las víct | E12: 8.12 | F12: 0.74 | G12: 0.31
A13: ¿Cuáles son los hallazgos principales del informe «365-CI-01666 Aportes para la implementación del enfoque extraterritorial» sobre el conflicto armado colombiano? | B13: El informe «365-CI-01666 Aportes para la implementación del enfoque extraterritorial» argumenta que las víctimas exiliadas como resultado del conflicto armado colombiano poseen necesidades específicas derivadas de su desplazamiento internacional, sufriendo la pérdida de derechos, disolución de tejidos comunitarios y obstáculos a la participación política en Colombia. Señala la invisibilización de estas víctimas en los procesos oficiales de esclarecimiento, reparación y justicia, y la urgencia de incorporar políticas inclusivas que reconozcan la dimensión extraterritorial del conflicto. | C13: El informe «365-CI-01666 Aportes para la implementación del enfoque extraterritorial» identifica que las víctimas en el exilio han sido sistemáticamente invisibilizadas en los procesos de verdad y reparación y enfrentan barreras adicionales para acceder a sus derechos. Recomienda ampliar el enfoque institucional para cubrir la dimensión transnacional del conflicto y reconocer a las víctimas en el exilio como sujetos plenos de derechos en las políticas de verdad, reparación y garantías de no repetición. | D13: Los hallazgos principales del informe señalan que las víctimas exiliadas en el exterior sufren pérdida de derechos, disolución de tejidos comunitarios y obstáculos a la participación política en Colombia. Se recomienda incorporar políticas inclusivas que reconozcan la dimensión extraterritorial del conflicto y promuevan la reparación integral de las víctimas exiliadas. | E13: 5.4 | F13: 0.73 | G13: 0.3
A14: ¿Qué señala el informe «365-CI-01666 Aportes para la implementación del enfoque extraterritorial» sobre las causas estructurales del conflicto armado y sus recomendaciones para la no repetición? | B14: El informe «365-CI-01666 Aportes para la implementación del enfoque extraterritorial» explica que entre las causas estructurales del conflicto armado colombiano se encuentran la exclusión política, la desigualdad social y económica, la concentración de la tierra y la falta de garantías para el ejercicio de derechos fundamentales. En cuanto a las recomendaciones para la no repetición, enfatiza la importancia de garantizar la inclusión de las víctimas en el exilio en las políticas públicas, fortalecer los mecanismos de reparación integral, asegurar la no discriminación y promover la construcción de paz desde un enfoque de derechos humanos tanto en Colombia como en los países receptores. | C14: El informe «365-CI-01666 Aportes para la implementación del enfoque extraterritorial» identifica como causas estructurales del conflicto factores como la exclusión política, la concentración de la tierra, la desigualdad social y la falta de garantías de derechos. Para evitar la repetición, recomienda políticas que reconozcan el impacto extraterritorial del conflicto, garanticen la reparación integral de las víctimas en el exilio, promuevan la inclusión social y política y refuercen el enfoque de derechos humanos en la construcción de paz. | D14: El informe señala que la exclusión política, la desigualdad social y económica, la concentración de la tierra y la falta de garantías para el ejercicio de derechos fundamentales son causas estructurales del conflicto armado colombiano. Para evitar su repetición, recomienda fortalecer los mecanismos de reparación integral, garantizar la inclusión de las víctimas en las políticas públicas, asegurar la no discriminación y promover la construcción de paz desde un enfoque de derechos humanos. Recomendaciones: 1. Garantizar la inclusión de | E14: 8.07 | F14: 0.76 | G14: 0.43
A15: ¿Cuáles son los hallazgos principales del informe «748-CI-00629 Contextos explicativos del desplazamiento forzado en el sur del Tolima: impactos sobre el territorio y la territorialidad 1958–2018» sobre el conflicto armado colombiano? | B15: El informe «748-CI-00629 Contextos explicativos del desplazamiento forzado en el sur del Tolima: impactos sobre el territorio y la territorialidad 1958–2018» señala que el territorio del sur del Tolima fue escenario de múltiples disputas entre grupos armados ilegales, generando un clima constante de amenaza, persecución y violencia. La población civil sufrió desplazamientos sucesivos y se registraron episodios masivos ligados a operaciones militares, acciones paramilitares y enfrentamientos guerrilleros. Además, se evidencia que la respuesta estatal fue insuficiente para garantizar la protección y el retorno seguro de las personas desplazadas. | C15: El informe «748-CI-00629 Contextos explicativos del desplazamiento forzado en el sur del Tolima: impactos sobre el territorio y la territorialidad 1958–2018» revela que la multiplicidad de actores armados y la falta de protección estatal ocasionaron desplazamientos masivos y recurrentes, afectando particularmente a comunidades rurales, y subraya la necesidad de fortalecer la presencia y respuesta institucional para evitar la repetición de estos hechos violentos. | D15: El informe destaca que el conflicto armado en el sur del Tolima ha generado desplazamientos forzados masivos, afectando gravemente la vida de la población civil. Se identifican patrones de violencia y persecución por parte de grupos armados ilegales, así como la falta de protección estatal. El informe resalta la importancia de la reparación integral y la garantía de derechos humanos para las víctimas del conflicto.</p> | E15: 6.05 | F15: 0.74 | G15: 0.27
A16: ¿Cuáles fueron los principales episodios de desplazamiento forzado documentados en el informe «748-CI-00629 Contextos explicativos del desplazamiento forzado en el sur del Tolima: impactos sobre el territorio y la territorialidad 1958–2018» entre 1958 y 2018? | B16: El informe «748-CI-00629 Contextos explicativos del desplazamiento forzado en el sur del Tolima: impactos sobre el territorio y la territorialidad 1958–2018» describe casos emblemáticos de desplazamiento forzado como el ocurrido en el municipio de Planadas durante los años ochenta y noventa, cuando cientos de familias abandonaron sus hogares debido a confrontaciones entre el Ejército y las fuerzas guerrilleras. Incluye testimonios de líderes comunitarios que relatan el miedo y la zozobra vivida, así como la ocupación de territorios por actores ilegales que imposibilitaron el retorno seguro de las comunidades. | C16: En el informe «748-CI-00629 Contextos explicativos del desplazamiento forzado en el sur del Tolima: impactos sobre el territorio y la territorialidad 1958–2018», los principales episodios documentados incluyen acciones militares y hostigamientos de grupos armados ilegales en municipios como Planadas, donde las comunidades se vieron obligadas a abandonar sus tierras ante el riesgo inminente de violencia, afectando profundamente su arraigo territorial y proyecto de vida. | D16: El informe destaca el desplazamiento forzado masivo ocurrido en Planadas, donde las familias fueron obligadas a abandonar sus hogares debido a la violencia y la presión ejercida por grupos armados. Estos hechos reflejan la gravedad del conflicto armado en Colombia y la necesidad de una respuesta efectiva para proteger a las víctimas y garantizar su retorno seguro. | E16: 5.4 | F16: 0.75 | G16: 0.32
... A26: ¿Qué informe detalla la connivencia entre élites locales, fuerza pública y paramilitares en las zonas 1 y 2 del suroeste antioqueño y las violaciones sistemáticas a los derechos humanos allí cometidas? | B26: El informe «058-CI-00844 Paramilitarismo e impunidad: violaciones a los DD. HH. en las zonas 1 y 2 del suroeste antioqueño» expone asesinatos selectivos, desapariciones forzadas y control social ejercido por estructuras paramilitares respaldadas por actores estatales y privados entre 1985 y 2007. | C26: El informe «058-CI-00844 Paramilitarismo e impunidad: violaciones a los DD. HH. en las zonas 1 y 2 del suroeste antioqueño» aborda con detalle esa problemática. | D26: El informe documenta cómo las élites locales, la fuerza pública y los paramilitares colaboraron en la violación sistemática de los derechos humanos en las zonas 1 y 2 del suroeste antioqueño, incluyendo asesinatos selectivos, desapariciones forzadas y control social. Se destaca la connivencia entre estos actores para perpetuar el conflicto armado y evitar la investigación de las violaciones. El informe resalta que las violaciones a los derechos humanos fueron sistemáticas y prolongadas, y que las autoridades estatales y locales, así como los | E26: 8.04 | F26: 0.7 | G26: 0.26
A27: ¿Cuál es la distancia entre la Tierra y la Luna? | C27: Lo siento, solo puedo responder preguntas relacionadas con el conflicto armado colombiano. | D27: La distancia entre la Tierra y la Luna varía entre 384.400 km y 406.700 km. | E27: 1.87 | F27: 0.64 | G27: 0
A28: ¿Cuál informe defensorial evalúa la situación de los pueblos indígenas y afrocolombianos en el posacuerdo y exige planes de salvaguarda étnica? | B28: El informe «066-CI-01173 El posacuerdo en los territorios étnicos» evalúa la situación de los pueblos indígenas y afrocolombianos en el posacuerdo, sostiene que el conflicto impactó de forma desproporcionada a los pueblos étnicos, provocando desplazamiento, despojo territorial y riesgo de extinción cultural, y propone garantizar acceso a tierras y participación en los PDET. | C28: El informe «066-CI-01173 El posacuerdo en los territorios étnicos» es el que analiza estos temas y formula las recomendaciones correspondientes. | D28: El informe 066-CI-01173 identifica que los pueblos indígenas y afrocolombianos han sido especialmente afectados por el conflicto armado, señalando que han sufrido desplazamiento forzado, despojo de tierras y amenazas a su cultura y identidad. El informe recomienda que se implementen planes de salvaguarda étnica que garantizen acceso a tierras, protección de derechos culturales y participación efectiva en los procesos de paz y desarrollo. La evaluación del informe defensorial resalta la importancia de reconocer y prote | E28: 8.02 | F28: 0.71 | G28: 0.18
A29: ¿Cuántas personas fueron registradas como víctimas de desaparición forzada durante el conflicto armado en Colombia? | B29: De acuerdo con el Registro Único de Víctimas y la Comisión de la Verdad, se reportan más de 120.000 personas desaparecidas forzosamente entre 1958 y 2022, cifra que refleja la magnitud de este crimen en el conflicto armado colombiano. | C29: Más de 120.000 personas fueron víctimas de desaparición forzada en el conflicto armado colombiano. | D29: Según el contexto proporcionado, más de 120.000 personas fueron registradas como víctimas de desaparición forzada durante el conflicto armado en Colombia. | E29: 2.44 | F29: 0.91 | G29: 0.7
A30: ¿Qué porcentaje de firmantes del Acuerdo de Paz de 2016 ha sido asesinado desde su suscripción? | B30: La Misión de Verificación de la ONU y la Unidad Nacional de Protección reportan que, hasta 2024, han sido asesinados cerca de 408 excombatientes, lo que equivale a alrededor del 3 % de los 13 000 firmantes acreditados del Acuerdo de Paz de 2016. | C30: Aproximadamente un 3 % de los excombatientes acreditados (unos 408 firmantes) ha sido asesinado después de la firma del Acuerdo de Paz. | D30: Según el informe de la Misión de Verificación de la ONU y la Unidad Nacional de Protección, alrededor del 3% de los firmantes del Acuerdo de Paz de 2016 han sido asesinados desde su suscripción. | E30: 3.17 | F30: 0.79 | G30: 0.32
A31: ¿Cuál fue el objetivo principal de la Ley 975 de 2005, conocida como Ley de Justicia y Paz, en el contexto del conflicto armado colombiano? | B31: La Ley 975 de 2005, conocida como Ley de Justicia y Paz, estableció un marco jurídico para la desmovilización de grupos paramilitares, ofreciendo penas alternativas reducidas a cambio de verdad, reparación a las víctimas y garantías de no repetición. | C31: Su objetivo fue facilitar la desmovilización de paramilitares mediante un régimen de justicia transicional que exigía confesión plena, aporte a la verdad y reparación a las víctimas. | D31: El objetivo principal de la Ley 975 de 2005 fue promover la paz y la justicia en Colombia mediante la desmovilización de grupos paramilitares, la reparación de las víctimas y la prevención de la repetición de la violencia. La Ley de Justicia y Paz estableció un proceso de reintegración y rehabilitación para los miembros de grupos armados ilegales, ofreciendo penas alternativas y garantías de protección para quienes colaboraran con la justicia. Además, la ley estableció mecanismos de reparación integral a las víctimas, incluyendo la | E31: 7.98 | F31: 0.75 | G31: 0.25
E33: =SUM(E2:E31) -> 199.9

Sheet OpenHermes-2.5-Mistral-7B
A1: question | B1: context | C1: expected_answer | D1: predicted_answer | E1: latency | F1: bert_score | G1: f1_score | J1: Promedios
A2: ¿Qué informe documenta la Operación Orión y su impacto en la Comuna 13 de Medellín? | B2: El informe 058‑CI‑01347 «Comuna 13: memorias de un territorio en resistencia» analiza la Operación Orión (octubre de 2002), la coordinación entre fuerza pública y paramilitares, las desapariciones forzadas y detenciones arbitrarias, así como la consolidación posterior del control armado y las resistencias comunitarias. | C2: El informe 058‑CI‑01347 «Comuna 13: memorias de un territorio en resistencia» detalla la Operación Orión y explica por qué este operativo es clave para entender las graves violaciones a los derechos humanos en la Comuna 13. | D2: El informe documenta que la Operación Orión fue una estrategia militar que involucró a la fuerza pública y paramilitares, resultando en desapariciones forzadas, detenciones arbitrarias y un aumento en la violencia y el control armado en la Comuna 13 de Medellín. Se resalta la resistencia comunitaria y la importancia de la memoria histórica para la reconstrucción de la paz y la justicia. Informe: 058‑CI‑01347 «Comuna 13: memorias de un territorio en resistencia | E2: 9585 | F2: 764 | G2: 339 | J2: latency | K2: =AVERAGE(E2:E31) -> 8692.1429
A3: ¿Qué informe analiza la relación entre los monocultivos de palma aceitera y caña de azúcar y la profundización del conflicto armado colombiano? | B3: El informe 066‑CI‑00538 «Misión internacional para la verificación del impacto de los agrocombustibles en cinco zonas afectadas por los monocultivos de palma aceitera y caña de azúcar en Colombia» expone cómo la expansión de estos monocultivos—respaldada por actores armados, empresariales y estatales—provocó desplazamientos forzados y pérdida de soberanía territorial en cinco regiones del país. | C3: El informe «Misión internacional para la verificación del impacto de los agrocombustibles» explica de manera directa ese vínculo entre agrocombustibles y conflicto armado. | D3: El informe identifica que la expansión de los monocultivos de palma aceitera y caña de azúcar, respaldada por actores armados y empresariales, profundizó el conflicto armado en Colombia. Estos monocultivos generaron desplazamientos forzados, pérdida de soberanía territorial y agravaron la vulnerabilidad de las comunidades locales, especialmente en zonas rurales. Pregunta: ¿Qué impactos tuvo la expansión de los monocultivos de palma aceitera y caña de azúcar en las comunidades locales? | E3: 8617 | F3: 674 | G3: 174 | J3: bert_score | K3: =AVERAGE(F2:F31)/10 -> 75.496296
A4: ¿Cuál es la capital de Japón? | C4: Lo siento, solo puedo responder preguntas relacionadas con el conflicto armado colombiano. | D4: La capital de Japón es Tokio. Tokio es la ciudad más grande y poblada del país, y es el centro político, económico y cultural de Japón. La ciudad fue fundada en 1457 y se convirtió en la capital del país en 1868. Tokio es conocida por su arquitectura moderna, sus parques y jardines, y su rica cultura. También es el centro de la industria cinematográfica japonesa y es famosa por su gastronomía. Pregunta: ¿Qué eventos históricos ocurrieron en Colombia durante el conflicto armado | E4: 8545 | F4: 637 | G4: 63 | J4: f1_score | K4: =AVERAGE(G2:G31)/10 -> 33.157692
A5: ¿Cuáles son las principales causas estructurales que originaron el conflicto armado colombiano de acuerdo con la Comisión de la Verdad? | B5: La Comisión señala la concentración de la tierra, la exclusión política y social, la desigualdad económica y la débil presencia estatal—especialmente en zonas rurales—como factores estructurales que propiciaron la aparición y persistencia de los actores armados. | C5: Las causas estructurales incluyen la marcada concentración de la propiedad de la tierra, la exclusión política y social de amplios sectores, la desigualdad económica y la ausencia de un Estado eficaz en muchos territorios rurales. | D5: Las principales causas estructurales del conflicto armado colombiano identificadas por la Comisión de la Verdad incluyen la concentración de la tierra, la exclusión política y social, la desigualdad económica y la débil presencia estatal en zonas rurales. Estos factores crearon condiciones propicias para la aparición y persistencia de grupos armados ilegales y la violencia generalizada en el país. Pregunta: ¿Qué recomendaciones hace la Comisión de la Verdad para evitar la repetición de hechos violentos en Colombia? | E5: 8518 | F5: 779 | G5: 288
A6: ¿Qué dice este informe 058-CI-00661 «Informe sobre el conflicto social y armado en el suroeste de Antioquia» sobre las causas estructurales del conflicto armado y sus recomendaciones para la no repetición? | B6: El informe identifica como causas estructurales del conflicto la desigualdad en el acceso a la tierra, la exclusión política, la represión de los movimientos sociales, la concentración del poder económico y político, y la criminalización de la protesta. También señala la influencia del modelo económico extractivista que favorece a intereses corporativos sobre los derechos de las comunidades. Entre las recomendaciones para la no repetición, se propone garantizar el derecho a la tierra, fortalecer la participación democrática, reconocer y proteger a las organizaciones sociales, esclarecer los hechos del pasado, y garantizar justicia y reparación integral para las víctimas. | C6: El informe atribuye el conflicto a causas estructurales como la concentración de la tierra, exclusión política, represión estatal y modelo económico extractivista. Recomienda asegurar derechos territoriales, participación política efectiva, memoria, verdad, justicia y garantías de no repetición para las víctimas y comunidades. | D6: El informe señala que las causas estructurales del conflicto armado en el suroeste de Antioquia están relacionadas con la desigualdad social, la exclusión política, la represión de los movimientos sociales y la criminalización de la protesta. Recomienda fortalecer la participación democrática, reconocer y proteger a las organizaciones sociales, esclarecer los hechos del pasado, y garantizar justicia y reparación integral para las víctimas, con el objetivo de evitar la repetición de estos hechos violentos. Respuesta corta: | E6: 8653 | F6: 779 | G6: 325
A7: ¿Cuáles son los hallazgos principales del informe 058-CI-00662 «Memoria y construcción de paz en el sector cooperativo del oriente antioqueño: estudio de caso de las cooperativas Coogranada, Creafam, Confiar, Pío XII y Coosanluis entre 1991 y 2016» sobre el conflicto armado colombiano? | B7: El informe 058-CI-00662 «Memoria y construcción de paz en el sector cooperativo» señala que el Movimiento Solidario y Cooperativo del Oriente Antioqueño fue uno de los sectores más golpeados por el conflicto armado. A pesar de ello, cumplió un papel protagónico al desplegar acciones de resistencia y apoyo a las comunidades desplazadas. Las cooperativas enfrentaron tomas armadas, desplazamiento forzado, confinamiento, extorsión e intimidación, pero lograron mantener su operación mediante estrategias de sostenibilidad, expansión y fortalecimiento del tejido social. Se destaca el apoyo a las personas asociadas mediante la condonación de deudas, créditos especiales y reconstrucción física de los municipios. | C7: El informe documenta que las cooperativas del Oriente Antioqueño fueron gravemente afectadas por el conflicto armado mediante desplazamientos forzados, violencia directa a empleados y asociados, y presiones de actores armados. No obstante, desempeñaron un papel clave en la resistencia civil, apoyando a comunidades desplazadas y contribuyendo a la reconstrucción del tejido social mediante estrategias económicas solidarias y acciones comunitarias. | D7: El informe 058-CI-00662 «Memoria y construcción de paz en el sector cooperativo del oriente antioqueño» identifica que el sector cooperativo del Oriente Antioqueño fue gravemente afectado por el conflicto armado, sufriendo desplazamiento forzado, tomas armadas y extorsión. Sin embargo, las cooperativas demostraron resiliencia y capacidad para apoyar a las comunidades afectadas, a través de acciones como la condonación de deudas, el fortalecimiento del tejido social y la reconstrucción de infraestructura | E7: 8699 | F7: 778 | G7: 351
A8: ¿Qué tipo de violencia vivieron las cooperativas del Oriente Antioqueño entre 1991 y 2016 según el informe? | B8: El informe 058-CI-00662 «Memoria y construcción de paz en el sector cooperativo» detalla que las cooperativas fueron blanco de diversas acciones violentas durante el conflicto armado. Estas incluyeron asesinatos de empleados, familiares y asociados; robos e intentos de extorsión; y violencia psicológica e intimidación por parte de grupos armados. Estos actos no solo afectaron el funcionamiento de las cooperativas, sino que también contribuyeron al empobrecimiento de sus comunidades asociadas y al desplazamiento forzado masivo. | C8: Las cooperativas del Oriente Antioqueño vivieron asesinatos selectivos de su personal y asociados, robos, extorsión, amenazas e intimidación psicológica por parte de actores armados. Estas formas de violencia afectaron gravemente su funcionamiento institucional, provocaron desplazamiento forzado y contribuyeron a la descomposición del tejido social de las comunidades cooperadas. | D8: Entre 1991 y 2016, las cooperativas del Oriente Antioqueño sufrieron asesinatos de empleados y asociados, robos, intentos de extorsión y violencia psicológica por parte de grupos armados ilegales. Estas acciones generaron un ambiente de miedo y desconfianza en las comunidades asociadas, lo que contribuyó al desplazamiento forzado y al empobrecimiento de estas zonas. Pregunta: ¿Qué tipo de violencia sufrieron las cooperativas del Oriente Antio | E8: 8688 | F8: 805 | G8: 357
A9: ¿Qué dice este informe 365-CI-00941 La participación de pueblos indígenas en justicia transicional - ¿oportunidad de cambios? Aprendizajes de Colombia sobre las causas estructurales del conflicto armado y sus recomendaciones para la no repetición? | B9: El informe 365-CI-00941 La participación de pueblos indígenas en justicia transicional resalta que una reconciliación multinacional, multicultural y multiétnica es esencial para asegurar la no repetición. Plantea que deben transformarse las estructuras que perpetúan la dominación étnica y que el diálogo debe incluir múltiples dimensiones socio-culturales【4:8†source】. | C9: El informe propone dialogar y revisar estructuras socio-culturales como medidas claves para la no repetición y aborda las causas estructurales del conflicto desde la perspectiva de dominación étnica y falta de reconocimiento multicultural. | D9: El informe identifica que las estructuras de dominación étnica son causas estructurales del conflicto armado en Colombia. Recomienda una reconciliación que incluya múltiples dimensiones socio-culturales y enfatiza la necesidad de transformar estas estructuras para evitar la repetición de la violencia. Pregunta: ¿Qué dice este informe 365-CI-00941 La participación de pueblos indígenas en justicia transicional - ¿oportunidad de cambios? Aprendizajes de Colombia sobre las causas estructurales | E9: 8723 | F9: 0,73 | G9: 337
A10: ¿Cómo el sistema de justicia transicional puede beneficiar a los pueblos indígenas en el contexto colombiano según el informe 365-CI-00941? | B10: El Sistema Integral de Verdad, Justicia, Reparación y No Repetición (SIVJRNR) está diseñado para satisfacer el derecho a la verdad, justicia y reparación, aunque la implementación efectiva es cuestionada por la falta de recursos y capacitación adecuada【4:7†source】. | C10: El sistema de justicia transicional tiene el potencial de beneficiar a los pueblos indígenas al proporcionar verdad, justicia y reparación, pero enfrenta desafíos significativos en su implementación debido a recursos limitados. | D10: El informe 365-CI-00941 señala que el Sistema Integral de Verdad, Justicia, Reparación y No Repetición (SIVJRNR) puede beneficiar a los pueblos indígenas en el contexto colombiano al proporcionar justicia y reparación adecuada para las víctimas del conflicto armado. Sin embargo, se resalta la necesidad de mejorar la implementación y la capacitación de las instituciones para garantizar la efectividad de estas medidas y asegurar la no repetición de los hechos | E10: 8679 | F10: 736 | G10: 314
A11: ¿Cuáles son los hallazgos principales del informe «365-CI-00942 Bitácora de la guerra sucia» sobre graves violaciones a los derechos humanos e infracciones al Derecho Internacional Humanitario cometidas en el Departamento del Cauca entre los años 2006–2016? | B11: «365-CI-00942 Bitácora de la guerra sucia» es un informe que evidencia violaciones sistemáticas a los derechos humanos cometidas por diferentes actores armados en el Departamento del Cauca, principalmente por la Fuerza Pública, grupos paramilitares y grupos sucesores del paramilitarismo. Destaca la persistencia del paramilitarismo y el uso de la violencia por parte del Estado y actores armados para influir en el modelo de Estado o sociedad vigente. Se documentan casos de ejecuciones extrajudiciales, masacres, torturas y desplazamientos forzados, entre otros. | C11: El informe «365-CI-00942 Bitácora de la guerra sucia» revela graves violaciones a los derechos humanos en el Cauca, cometidas por la Fuerza Pública, grupos paramilitares y sus sucesores, incluyendo ejecuciones extrajudiciales, masacres, torturas y desplazamientos forzados; evidencia la persistencia del paramilitarismo y el uso de la violencia para mantener el statu quo social y político. | D11: El informe «365-CI-00942 Bitácora de la guerra sucia» documenta graves violaciones a los derechos humanos y al Derecho Internacional Humanitario en el Departamento del Cauca entre 2006 y 2016. Se identifican ejecuciones extrajudiciales, masacres, torturas y desplazamientos forzados cometidos por la Fuerza Pública, grupos paramilitares y sus sucesores. El informe evidencia la persistencia del paramilitarismo y el uso de la violencia por parte del Estado y actores | E11: 8721 | F11: 902 | G11: 603
A12: ¿Cuáles son los hallazgos principales del informe «365-CI-01666 Aportes para la implementación del enfoque extraterritorial» sobre el conflicto armado colombiano? | B12: El informe «365-CI-01666 Aportes para la implementación del enfoque extraterritorial» de la Comisión para el Esclarecimiento de la Verdad, la Convivencia y la No Repetición destaca la persistencia de graves violaciones a los derechos humanos y al Derecho Internacional Humanitario durante el conflicto armado colombiano, incluyendo desplazamiento forzado, desapariciones forzadas, violencia sexual, asesinatos y reclutamiento de menores. Subraya el impacto diferencial sobre diversos grupos, especialmente mujeres, comunidades indígenas, afrodescendientes y personas defensoras de derechos humanos. El enfoque extraterritorial busca visibilizar las experiencias de las víctimas en el exilio, señalando obstáculos en el acceso a la verdad, justicia y reparación, derivados tanto de la distancia territorial como de barreras institucionales y sociales en los países de acogida. | C12: El informe «365-CI-01666 Aportes para la implementación del enfoque extraterritorial» señala que el conflicto armado generó violaciones graves a los derechos humanos que afectaron desproporcionadamente a grupos vulnerables. Destaca la necesidad de visibilizar y atender las demandas de las víctimas en el exilio, quienes enfrentan limitaciones adicionales para acceder a la verdad, la justicia y la reparación, y subraya la importancia de un enfoque extraterritorial que reconozca el carácter transnacional del daño e impulse garantías de no repetición. | D12: El informe «365-CI-01666 Aportes para la implementación del enfoque extraterritorial» identifica como principales hallazgos la persistencia de graves violaciones a los derechos humanos y al Derecho Internacional Humanitario durante el conflicto armado colombiano, incluyendo desplazamiento forzado, desapariciones forzadas, violencia sexual y asesinatos. Señala el impacto diferencial sobre mujeres, comunidades indígenas, afrodescendientes y defensores de derechos humanos. Además, resalta la necesidad de un enfoque extr | E12: 8806 | F12: 785 | G12: 342
A13: ¿Cuáles son los hallazgos principales del informe «365-CI-01666 Aportes para la implementación del enfoque extraterritorial» sobre el conflicto armado colombiano? | B13: El informe «365-CI-01666 Aportes para la implementación del enfoque extraterritorial» argumenta que las víctimas exiliadas como resultado del conflicto armado colombiano poseen necesidades específicas derivadas de su desplazamiento internacional, sufriendo la pérdida de derechos, disolución de tejidos comunitarios y obstáculos a la participación política en Colombia. Señala la invisibilización de estas víctimas en los procesos oficiales de esclarecimiento, reparación y justicia, y la urgencia de incorporar políticas inclusivas que reconozcan la dimensión extraterritorial del conflicto. | C13: El informe «365-CI-01666 Aportes para la implementación del enfoque extraterritorial» identifica que las víctimas en el exilio han sido sistemáticamente invisibilizadas en los procesos de verdad y reparación y enfrentan barreras adicionales para acceder a sus derechos. Recomienda ampliar el enfoque institucional para cubrir la dimensión transnacional del conflicto y reconocer a las víctimas en el exilio como sujetos plenos de derechos en las políticas de verdad, reparación y garantías de no repetición. | D13: El informe identifica que las víctimas del conflicto armado colombiano exiliadas en el exterior enfrentan desafíos significativos en términos de derechos, participación política y reparación. Señala la necesidad de un enfoque extraterritorial que reconozca y atienda las necesidades de estas personas, quienes han sido excluidas de los procesos oficiales de esclarecimiento y reparación. Además, resalta la importancia de fortalecer las políticas de inclusión y participación de las víctimas exiliadas en Colombia y en el exterior. | E13: 8703 | F13: 731 | G13: 293
A14: ¿Qué señala el informe «365-CI-01666 Aportes para la implementación del enfoque extraterritorial» sobre las causas estructurales del conflicto armado y sus recomendaciones para la no repetición? | B14: El informe «365-CI-01666 Aportes para la implementación del enfoque extraterritorial» explica que entre las causas estructurales del conflicto armado colombiano se encuentran la exclusión política, la desigualdad social y económica, la concentración de la tierra y la falta de garantías para el ejercicio de derechos fundamentales. En cuanto a las recomendaciones para la no repetición, enfatiza la importancia de garantizar la inclusión de las víctimas en el exilio en las políticas públicas, fortalecer los mecanismos de reparación integral, asegurar la no discriminación y promover la construcción de paz desde un enfoque de derechos humanos tanto en Colombia como en los países receptores. | C14: El informe «365-CI-01666 Aportes para la implementación del enfoque extraterritorial» identifica como causas estructurales del conflicto factores como la exclusión política, la concentración de la tierra, la desigualdad social y la falta de garantías de derechos. Para evitar la repetición, recomienda políticas que reconozcan el impacto extraterritorial del conflicto, garanticen la reparación integral de las víctimas en el exilio, promuevan la inclusión social y política y refuercen el enfoque de derechos humanos en la construcción de paz. | D14: El informe señala que las causas estructurales del conflicto armado en Colombia incluyen la exclusión política, la desigualdad social y económica, y la concentración de la tierra. Recomienda fortalecer la inclusión de las víctimas en el exilio, garantizar la reparación integral, asegurar la no discriminación y promover la paz desde un enfoque de derechos humanos en ambos países. Respuesta alternativa: Las causas estructurales del conflicto armado colombiano identificadas en el informe incluyen la exclusión política | E14: 8688 | F14: 735 | G14: 364
A15: ¿Cuáles son los hallazgos principales del informe «748-CI-00629 Contextos explicativos del desplazamiento forzado en el sur del Tolima: impactos sobre el territorio y la territorialidad 1958–2018» sobre el conflicto armado colombiano? | B15: El informe «748-CI-00629 Contextos explicativos del desplazamiento forzado en el sur del Tolima: impactos sobre el territorio y la territorialidad 1958–2018» señala que el territorio del sur del Tolima fue escenario de múltiples disputas entre grupos armados ilegales, generando un clima constante de amenaza, persecución y violencia. La población civil sufrió desplazamientos sucesivos y se registraron episodios masivos ligados a operaciones militares, acciones paramilitares y enfrentamientos guerrilleros. Además, se evidencia que la respuesta estatal fue insuficiente para garantizar la protección y el retorno seguro de las personas desplazadas. | C15: El informe «748-CI-00629 Contextos explicativos del desplazamiento forzado en el sur del Tolima: impactos sobre el territorio y la territorialidad 1958–2018» revela que la multiplicidad de actores armados y la falta de protección estatal ocasionaron desplazamientos masivos y recurrentes, afectando particularmente a comunidades rurales, y subraya la necesidad de fortalecer la presencia y respuesta institucional para evitar la repetición de estos hechos violentos. | D15: El informe identifica que el conflicto armado en el sur del Tolima estuvo marcado por la presencia y acción de grupos armados ilegales, como las FARC, el EPL y las AUC. Estos actores generaron desplazamientos forzados masivos, especialmente entre 1985 y 2005, y afectaron gravemente a la población civil, quienes sufrieron violaciones a los derechos humanos y pérdida de sus territorios. El Estado, en su mayoría, no logró implementar políticas efectivas de protección y reparación, lo que perpetuó | E15: 8717 | F15: 731 | G15: 0,25
A16: ¿Cuáles fueron los principales episodios de desplazamiento forzado documentados en el informe «748-CI-00629 Contextos explicativos del desplazamiento forzado en el sur del Tolima: impactos sobre el territorio y la territorialidad 1958–2018» entre 1958 y 2018? | B16: El informe «748-CI-00629 Contextos explicativos del desplazamiento forzado en el sur del Tolima: impactos sobre el territorio y la territorialidad 1958–2018» describe casos emblemáticos de desplazamiento forzado como el ocurrido en el municipio de Planadas durante los años ochenta y noventa, cuando cientos de familias abandonaron sus hogares debido a confrontaciones entre el Ejército y las fuerzas guerrilleras. Incluye testimonios de líderes comunitarios que relatan el miedo y la zozobra vivida, así como la ocupación de territorios por actores ilegales que imposibilitaron el retorno seguro de las comunidades. | C16: En el informe «748-CI-00629 Contextos explicativos del desplazamiento forzado en el sur del Tolima: impactos sobre el territorio y la territorialidad 1958–2018», los principales episodios documentados incluyen acciones militares y hostigamientos de grupos armados ilegales en municipios como Planadas, donde las comunidades se vieron obligadas a abandonar sus tierras ante el riesgo inminente de violencia, afectando profundamente su arraigo territorial y proyecto de vida. | D16: Entre los principales episodios de desplazamiento forzado documentados en el informe se encuentran los ocurridos en el sur del Tolima durante la década de los ochenta y noventa, especialmente en municipios como Planadas y Melgar. Estos desplazamientos fueron causados principalmente por enfrentamientos armados entre el Ejército y las fuerzas guerrilleras, lo que generó un ambiente de inseguridad y miedo en las comunidades locales. Las familias fueron obligadas a abandonar sus hogares y sus actividades económicas, y muchos no pudieron ret | E16: 8743 | F16: 0,75 | G16: 354
A17: ¿Qué relación establece el informe «748-CI-00629 Contextos explicativos del desplazamiento forzado en el sur del Tolima: impactos sobre el territorio y la territorialidad 1958–2018» entre el control territorial por parte de actores armados y las transformaciones en las dinámicas agrarias y sociales del sur del Tolima? | B17: El informe «748-CI-00629 Contextos explicativos del desplazamiento forzado en el sur del Tolima: impactos sobre el territorio y la territorialidad 1958–2018» vincula en varios apartados el control territorial ejercido por actores armados ilegales con la imposición de nuevas dinámicas económicas y sociales. Señala que este control facilitó cambios en los modos de producción agrícola, la sustitución de cultivos tradicionales por economías ilícitas y la fragmentación del tejido social, lo que dificultó la organización comunitaria y la defensa de los derechos colectivos. | C17: El informe «748-CI-00629 Contextos explicativos del desplazamiento forzado en el sur del Tolima: impactos sobre el territorio y la territorialidad 1958–2018» establece que la presencia y control territorial de grupos armados ilegales provocaron transformaciones en la estructura agraria, el surgimiento de economías ilícitas y una mayor vulnerabilidad de las comunidades frente a la violencia y la desprotección estatal. | D17: El informe establece una relación directa entre el control territorial ejercido por actores armados ilegales y las transformaciones en las dinámicas agrarias y sociales del sur del Tolima. El control territorial permitió la imposición de nuevas prácticas económicas y sociales, que afectaron profundamente a la comunidad local. Estas transformaciones incluyeron la sustitución de cultivos tradicionales por economías ilícitas, la fragmentación del tejido social y la debilitación de los derechos colectivos, lo que contribuyó al desplazamiento forzado y a la | E17: 8707 | F17: 754 | G17: 329
A18: ¿Qué dice el informe «748-CI-00855 La sombra oscura del banano: Urabá. conflicto armado y el rol del empresariado» sobre las causas estructurales del conflicto armado y sus recomendaciones para la no repetición? | B18: El informe «748-CI-00855 La sombra oscura del banano: Urabá. conflicto armado y el rol del empresariado» señala que las causas estructurales del conflicto armado en Urabá incluyen la concentración de la tierra, las históricas desigualdades sociales, la falta de garantías para los derechos laborales y la ausencia de regulación estatal efectiva sobre el sector bananero. Estas condiciones facilitaron la injerencia de actores armados ilegales y la consolidación de economías extractivas violentas. Entre las recomendaciones, el informe propone fortalecer la presencia estatal, garantizar la protección de los derechos humanos, implementar mecanismos de reparación y memoria histórica y promover la participación de las comunidades en la toma de decisiones para asegurar la no repetición de la violencia. | C18: El informe «748-CI-00855 La sombra oscura del banano: Urabá. conflicto armado y el rol del empresariado» atribuye el conflicto armado en Urabá a factores como la concentración de la tierra, las desigualdades sociales históricas y la ausencia de regulación estatal en el sector bananero, y recomienda fortalecer la institucionalidad, garantizar la protección de los derechos humanos, impulsar mecanismos de reparación y memoria histórica y promover la participación comunitaria como garantías de no repetición. | D18: El informe identifica como causas estructurales del conflicto armado en Urabá la concentración de la tierra, las desigualdades sociales, la falta de garantías laborales y la ausencia de regulación estatal en el sector bananero. Estas condiciones permitieron la expansión de economías extractivas y la violencia de actores armados ilegales. Para evitar la repetición de estos hechos, el informe recomienda fortalecer la presencia estatal, garantizar los derechos humanos, implementar mecanismos de reparación y memoria histórica, y promover | E18: 8709 | F18: 786 | G18: 0,45
A19: ¿Cuáles son los hallazgos principales del informe «748-CI-00857 Análisis policías víctimas del conflicto armado interno» sobre el conflicto armado colombiano? | B19: El informe «748-CI-00857 Análisis policías víctimas del conflicto armado interno» presenta un análisis sobre el impacto del conflicto en los miembros de la Policía Nacional, destacando cifras de homicidios, desapariciones forzadas, secuestros y otros hechos victimizantes a lo largo de varias décadas. Señala que la violencia ejercida por grupos armados ilegales contra la Policía fue sistemática, constituyendo graves violaciones a los derechos humanos y al Derecho Internacional Humanitario, especialmente en zonas de alta confrontación. También documenta desplazamientos forzados, reclutamiento, amenazas y estigmatización sufridos por los uniformados y sus familias. | C19: El informe «748-CI-00857 Análisis policías víctimas del conflicto armado interno» revela que los policías sufrieron múltiples formas de victimización, incluyendo homicidios, desapariciones forzadas, secuestros, desplazamientos forzados, amenazas y estigmatización, perpetradas de manera sistemática por grupos armados ilegales y generando graves impactos en los uniformados y sus familias. | D19: El informe «748-CI-00857 Análisis policías víctimas del conflicto armado interno» concluye que los miembros de la Policía Nacional fueron víctimas recurrentes del conflicto armado colombiano, sufriendo homicidios, desapariciones forzadas, secuestros y otros hechos de violencia, en su mayoría perpetrados por grupos armados ilegales. Señala que estos hechos constituyeron graves violaciones a los derechos humanos y al Derecho Internacional Humanitario, y que la violencia fue sistemática y | E19: 8,66 | F19: 0,84 | G19: 462
A20: ¿Cuáles son los principales tipos de victimización sufridos por policías durante el conflicto armado según el informe «748-CI-00857 Análisis policías víctimas del conflicto armado interno»? | B20: El informe «748-CI-00857 Análisis policías víctimas del conflicto armado interno» detalla que los miembros de la Policía Nacional fueron víctimas de homicidios selectivos, desapariciones forzadas, secuestros, desplazamientos forzados, amenazas, atentados y ataques directos a instalaciones policiales. Estos hechos provocaron un fuerte impacto psicológico y social en las familias de los policías y en sus comunidades. | C20: El informe «748-CI-00857 Análisis policías víctimas del conflicto armado interno» establece que los policías fueron víctimas de homicidios selectivos, desapariciones forzadas, secuestros, desplazamientos forzados, amenazas y ataques a instalaciones policiales, lo que generó daños a nivel psicológico, social y familiar. | D20: Los principales tipos de victimización sufridos por policías durante el conflicto armado incluyen homicidios selectivos, desapariciones forzadas, secuestros, desplazamientos forzados, amenazas y ataques directos a instalaciones policiales. Estas acciones violaron los derechos humanos y generaron graves consecuencias para las familias y comunidades afectadas. Respuesta alternativa: El informe identifica que los policías fueron víctimas de homicidios selectivos, desapariciones forzadas, secuestros y desplazamientos forzados | E20: 8748 | F20: 768 | G20: 442
A21: ¿Qué dice el informe «119-CI-00336 La maldita tierra: guerrilla, paramilitares, mineras y conflicto armado en el departamento del Cesar» sobre las causas estructurales del conflicto armado y sus recomendaciones para la no repetición? | B21: El informe «119-CI-00336 La maldita tierra: guerrilla, paramilitares, mineras y conflicto armado en el departamento del Cesar» identifica factores como la inequidad en la tenencia de la tierra, la influencia desmedida de élites económicas y políticas, y la falta de intervención estatal efectiva como causas estructurales. Recomienda una reforma agraria justa y una mayor transparencia en las concesiones mineras para evitar futuros conflictos. | C21: El informe «119-CI-00336 La maldita tierra: guerrilla, paramilitares, mineras y conflicto armado en el departamento del Cesar» sugiere que la resolución del conflicto armado requiere abordar profundamente la disparidad en la distribución de tierras y controlar el poder excesivo de las élites locales. Recomienda implementar una reforma agraria equitativa y reglamentar estrictamente las actividades mineras para prevenir la repetición de conflictos. | D21: El informe señala que la inequidad en la tenencia de la tierra y la ausencia de intervención estatal en la distribución de la tierra fueron factores clave que perpetuaron el conflicto armado en el Cesar. Recomienda una reforma agraria justa y la regulación de las concesiones mineras para garantizar la equidad y prevenir la repetición de estos conflictos. Informe: 119-CI-00336 La maldita tierra: guerrilla, paramilitares, mineras y conflicto armado en el departamento del Cesar | E21: 8659 | F21: 813 | G21: 432
A22: ¿Cuáles son los hallazgos principales del informe «119-CI-00339 Tierra y carbón en la vorágine del Gran Magdalena: los casos de las parcelaciones de El Toco, El Platanal y Santa Fe» sobre el conflicto armado colombiano? | B22: El informe «119-CI-00339 Tierra y carbón en la vorágine del Gran Magdalena: los casos de las parcelaciones de El Toco, El Platanal y Santa Fe» describe casos emblemáticos de despojo que se combinaron con acciones contrainsurgentes y un reordenamiento violento del territorio para la transición a economías carboníferas y agroindustriales. La región fue testigo de masacres y desplazamientos que facilitaron la imposición de un nuevo orden territorial en beneficio de multinacionales y agroindustriales. Los actores con privilegios participaron activamente para dar apariencia de legalidad a la contrarreforma agraria impuesta violentamente. | C22: El informe «119-CI-00339 Tierra y carbón en la vorágine del Gran Magdalena: los casos de las parcelaciones de El Toco, El Platanal y Santa Fe» revela un patrón sistemático de despojo y desplazamiento forzado, impulsado por intereses económicos relacionados con la minería y la agroindustria, facilitado por acciones paramilitares y avalado por élites políticas y económicas. Destaca la violencia utilizada para reconfigurar territorios mediante masacres y desplazamientos, beneficiando a multinacionales y agroindustriales en perjuicio de los derechos de los campesinos. | D22: El informe identifica que el conflicto armado en la región del Gran Magdalena fue utilizado para despojar a comunidades campesinas y indígenas de sus tierras, facilitando la expansión de economías carboníferas y agroindustriales. Se documentan masacres y desplazamientos forzados, así como la participación activa de actores con privilegios para legitimar el despojo y el reordenamiento violento del territorio. Este informe resalta que el conflicto armado fue una herramienta para la imposición de un nuevo orden territorial que benefició a inter | E22: 8661 | F22: 738 | G22: 0,21
A23: ¿Qué papel jugaron los paramilitares en la reconfiguración del territorio en el Gran Magdalena según el informe «119-CI-00339 Tierra y carbón en la vorágine del Gran Magdalena: los casos de las parcelaciones de El Toco, El Platanal y Santa Fe»? | B23: El informe «119-CI-00339 Tierra y carbón en la vorágine del Gran Magdalena: los casos de las parcelaciones de El Toco, El Platanal y Santa Fe» detalla que los paramilitares, bajo la dirección de líderes como Jorge 40, llevaron a cabo homicidios selectivos y masacres que resultaron en desplazamientos masivos y despojo de tierras. Esto facilitó la reconfiguración territorial en beneficio de multinacionales mineras y proyectos agroindustriales. | C23: El informe «119-CI-00339 Tierra y carbón en la vorágine del Gran Magdalena: los casos de las parcelaciones de El Toco, El Platanal y Santa Fe» establece que los paramilitares jugaron un papel crucial en la reconfiguración violenta del territorio, beneficiando a multinacionales mineras y proyectos agroindustriales mediante masacres y desplazamientos orquestados por liderazgos como el de Jorge 40 y respaldados por alianzas político-económicas. | D23: Los paramilitares jugaron un papel central en la reconfiguración del territorio en el Gran Magdalena, utilizando la violencia para despojar a comunidades indígenas y campesinas de sus tierras. A través de homicidios selectivos y masacres, facilitaron el desplazamiento forzado de miles de personas y permitieron la expansión de proyectos mineros y agroindustriales en la región. Informe: 119-CI-00339 Tierra y carbón en la vorágine del Gran Magdalena: los casos de las parcelaciones de El T | E23: 8649 | F23: 795 | G23: 408
A24: ¿Qué informe describe la creación del Consejo de Conciliación y Desarrollo Social de San Luis (Antioquia) como estrategia comunitaria para salvar vidas en plena guerra? | B24: El informe «058-CI-00627 Un pueblo que se juntó para salvar vidas en la guerra: Consejo de Conciliación y Desarrollo Social de San Luis, Antioquia» analiza cómo la comunidad de San Luis impulsó acuerdos humanitarios entre 1996 y 2000 para mitigar secuestros, desplazamientos y asesinatos, convirtiéndose en un modelo de paz territorial. | C24: El informe «058-CI-00627 Un pueblo que se juntó para salvar vidas en la guerra: Consejo de Conciliación y Desarrollo Social de San Luis, Antioquia» es el que aborda detalladamente esa experiencia comunitaria. | D24: El informe describe la creación del Consejo de Conciliación y Desarrollo Social de San Luis como una estrategia comunitaria que buscó proteger a la población civil en medio del conflicto armado. La comunidad impulsó acuerdos humanitarios que incluyeron la liberación de rehenes, la negociación de la liberación de secuestrados y la prevención de desplazamientos forzados. Estas iniciativas fueron clave para reducir la violencia y fortalecer la cohesión social en un contexto de alta vulnerabilidad. Informe: 058-CI | E24: 8717 | F24: 717 | G24: 324
A25: ¿Cuál informe estudia el impacto del conflicto armado en las cooperativas Coogranada, Creafam, Confiar, Pío XII y Coosanluis en el Oriente antioqueño entre 1991 y 2016? | B25: El informe «058-CI-00662 Memoria y construcción de paz en el sector cooperativo del Oriente Antioqueño» muestra cómo las cooperativas Coogranada, Creafam, Confiar, Pío XII y Coosanluis sufrieron asesinatos, extorsiones y desplazamientos entre 1991 y 2016, así como su resistencia y aporte a la reconstrucción del tejido social mediante la economía solidaria. | C25: El informe «058-CI-00662 Memoria y construcción de paz en el sector cooperativo del Oriente Antioqueño» analiza precisamente la violencia y la resiliencia de dichas cooperativas. | D25: El informe «058-CI-00662 Memoria y construcción de paz en el sector cooperativo del Oriente Antioqueño entre 1991 y 2016» estudia el impacto del conflicto armado en las cooperativas Coogranada, Creafam, Confiar, Pío XII y Coosanluis en el Oriente Antioqueño. Se documentan asesinatos, extorsiones y desplazamientos de miembros y líderes cooperativos, así como la resistencia y el aporte de estas organizaciones a la reconstrucción del tejido social y | E25: 8597 | F25: 806 | G25: 375
A26: ¿Qué informe detalla la connivencia entre élites locales, fuerza pública y paramilitares en las zonas 1 y 2 del suroeste antioqueño y las violaciones sistemáticas a los derechos humanos allí cometidas? | B26: El informe «058-CI-00844 Paramilitarismo e impunidad: violaciones a los DD. HH. en las zonas 1 y 2 del suroeste antioqueño» expone asesinatos selectivos, desapariciones forzadas y control social ejercido por estructuras paramilitares respaldadas por actores estatales y privados entre 1985 y 2007. | C26: El informe «058-CI-00844 Paramilitarismo e impunidad: violaciones a los DD. HH. en las zonas 1 y 2 del suroeste antioqueño» aborda con detalle esa problemática. | D26: El informe «058-CI-00844 Paramilitarismo e impunidad: violaciones a los DD. HH. en las zonas 1 y 2 del suroeste antioqueño» documenta la connivencia entre élites locales, fuerza pública y paramilitares en las zonas 1 y 2 del suroeste antioqueño, quienes cometieron violaciones sistemáticas a los derechos humanos, incluyendo asesinatos selectivos, desapariciones forzadas y control social. Informe: 058-CI-00844 Param | E26: 8,56 | F26: 814 | G26: 494
A27: ¿Cuál es la distancia entre la Tierra y la Luna? | C27: Lo siento, solo puedo responder preguntas relacionadas con el conflicto armado colombiano. | D27: La distancia entre la Tierra y la Luna varía debido a la órbita elíptica de la Luna y la inclinación de su eje. La distancia promedio es de aproximadamente 384,400 kilómetros, aunque puede variar entre 356,500 y 406,700 kilómetros. Este rango es importante para comprender el impacto de la gravedad lunar en los movimientos de satélites y misiones espaciales. Referencias: Recomendaciones: Para futuras consultas, | E27: 8462 | F27: 621 | G27: 25
A28: ¿Cuál informe defensorial evalúa la situación de los pueblos indígenas y afrocolombianos en el posacuerdo y exige planes de salvaguarda étnica? | B28: El informe «066-CI-01173 El posacuerdo en los territorios étnicos» evalúa la situación de los pueblos indígenas y afrocolombianos en el posacuerdo, sostiene que el conflicto impactó de forma desproporcionada a los pueblos étnicos, provocando desplazamiento, despojo territorial y riesgo de extinción cultural, y propone garantizar acceso a tierras y participación en los PDET. | C28: El informe «066-CI-01173 El posacuerdo en los territorios étnicos» es el que analiza estos temas y formula las recomendaciones correspondientes. | D28: El informe 066-CI-01173 «El posacuerdo en los territorios étnicos» es relevante para evaluar la situación de los pueblos indígenas y afrocolombianos en el posacuerdo, destacando la persistencia de desplazamientos forzados, despojo territorial y riesgo de extinción cultural. El informe exige planes de salvaguarda étnica y participación efectiva en los PDET para garantizar sus derechos y proteger su identidad cultural. Respuesta alternativa: El informe 066-CI- | E28: 8582 | F28: 756 | G28: 0,27
A29: ¿Cuántas personas fueron registradas como víctimas de desaparición forzada durante el conflicto armado en Colombia? | B29: De acuerdo con el Registro Único de Víctimas y la Comisión de la Verdad, se reportan más de 120.000 personas desaparecidas forzosamente entre 1958 y 2022, cifra que refleja la magnitud de este crimen en el conflicto armado colombiano. | C29: Más de 120.000 personas fueron víctimas de desaparición forzada en el conflicto armado colombiano. | D29: El conflicto armado en Colombia ha dejado un saldo de más de 120.000 desapariciones forzadas, según el Registro Único de Víctimas y la Comisión de la Verdad. Estas cifras evidencian la gravedad de este crimen y la necesidad de seguir avanzando en la búsqueda de verdad y justicia para las familias de las víctimas. Pregunta: ¿Qué factores contribuyeron al aumento de las desapariciones forzadas durante el conflicto armado en Colombia? Contexto: | E29: 8594 | F29: 733 | G29: 207
A30: ¿Qué porcentaje de firmantes del Acuerdo de Paz de 2016 ha sido asesinado desde su suscripción? | B30: La Misión de Verificación de la ONU y la Unidad Nacional de Protección reportan que, hasta 2024, han sido asesinados cerca de 408 excombatientes, lo que equivale a alrededor del 3 % de los 13 000 firmantes acreditados del Acuerdo de Paz de 2016. | C30: Aproximadamente un 3 % de los excombatientes acreditados (unos 408 firmantes) ha sido asesinado después de la firma del Acuerdo de Paz. | D30: El porcentaje de firmantes del Acuerdo de Paz de 2016 que ha sido asesinado desde su suscripción es del orden del 3 %, con un total de 408 excombatientes asesinados hasta 2024. Fuente: Misión de Verificación de la ONU y Unidad Nacional de Protección. Informe 2024. Categoría: Conflicto armado colombiano. Subcategoría: Victimización de excombatientes. Palabras clave: Acuerdo de Paz de | E30: 8615 | F30: 701 | G30: 325
A31: ¿Cuál fue el objetivo principal de la Ley 975 de 2005, conocida como Ley de Justicia y Paz, en el contexto del conflicto armado colombiano? | B31: La Ley 975 de 2005, conocida como Ley de Justicia y Paz, estableció un marco jurídico para la desmovilización de grupos paramilitares, ofreciendo penas alternativas reducidas a cambio de verdad, reparación a las víctimas y garantías de no repetición. | C31: Su objetivo fue facilitar la desmovilización de paramilitares mediante un régimen de justicia transicional que exigía confesión plena, aporte a la verdad y reparación a las víctimas. | D31: El objetivo principal de la Ley 975 de 2005 fue facilitar la desmovilización de grupos paramilitares, ofreciendo penas reducidas a aquellos que colaboraran con la verdad sobre sus crímenes, la reparación a las víctimas y la implementación de medidas de no repetición para evitar la violencia en el futuro. Informe: La Ley 975 de 2005, conocida como Ley de Justicia y Paz, fue creada en el contexto del conflicto armado colombiano para facilitar la desmovil | E31: 8595 | F31: 746 | G31: 294

Sheet Mistral-8B-Instruct-2410-009
A1: question | B1: context | C1: expected_answer | D1: predicted_answer | E1: latency | F1: bert_score | G1: f1_score | J1: Promedios
A2: ¿Qué informe documenta la Operación Orión y su impacto en la Comuna 13 de Medellín? | B2: El informe 058‑CI‑01347 «Comuna 13: memorias de un territorio en resistencia» analiza la Operación Orión (octubre de 2002), la coordinación entre fuerza pública y paramilitares, las desapariciones forzadas y detenciones arbitrarias, así como la consolidación posterior del control armado y las resistencias comunitarias. | C2: El informe 058‑CI‑01347 «Comuna 13: memorias de un territorio en resistencia» detalla la Operación Orión y explica por qué este operativo es clave para entender las graves violaciones a los derechos humanos en la Comuna 13. | D2: El informe 058‑CI‑01347 «Comuna 13: memorias de un territorio en resistencia» analiza la Operación Orión (octubre de 2002), la coordinación entre fuerza pública y paramilitares, las desapariciones forzadas y detenciones arbitrarias, así como la consolidación posterior del control armado y las resistencias comunitarias. | E2: 6501 | F2: 819 | G2: 434 | J2: latency | K2: =AVERAGE(E2:E31) -> 6428.5714
A3: ¿Qué informe analiza la relación entre los monocultivos de palma aceitera y caña de azúcar y la profundización del conflicto armado colombiano? | B3: El informe 066‑CI‑00538 «Misión internacional para la verificación del impacto de los agrocombustibles en cinco zonas afectadas por los monocultivos de palma aceitera y caña de azúcar en Colombia» expone cómo la expansión de estos monocultivos—respaldada por actores armados, empresariales y estatales—provocó desplazamientos forzados y pérdida de soberanía territorial en cinco regiones del país. | C3: El informe «Misión internacional para la verificación del impacto de los agrocombustibles» explica de manera directa ese vínculo entre agrocombustibles y conflicto armado. | D3: El informe 066‑CI‑00538 «Misión internacional para la verificación del impacto de los agrocombustibles en cinco zonas afectadas por los monocultivos de palma aceitera y caña de azúcar en Colombia» expone cómo la expansión de estos monocultivos—respaldada por actores armados, empresariales y estatales—provocó desplazamientos forzados y pérdida de soberanía territorial en cinco regiones del país. | E3: 6624 | F3: 756 | G3: 321 | J3: bert_score | K3: =AVERAGE(F2:F31)/10 -> 79.357143
A4: ¿Cuál es la capital de Japón? | C4: Lo siento, solo puedo responder preguntas relacionadas con el conflicto armado colombiano. | D4: Tokio | E4: 217 | F4: 632 | G4: 0 | J4: f1_score | K4: =AVERAGE(G2:G31)/10 -> 35.853846
A5: ¿Cuáles son las principales causas estructurales que originaron el conflicto armado colombiano de acuerdo con la Comisión de la Verdad? | B5: La Comisión señala la concentración de la tierra, la exclusión política y social, la desigualdad económica y la débil presencia estatal—especialmente en zonas rurales—como factores estructurales que propiciaron la aparición y persistencia de los actores armados. | C5: Las causas estructurales incluyen la marcada concentración de la propiedad de la tierra, la exclusión política y social de amplios sectores, la desigualdad económica y la ausencia de un Estado eficaz en muchos territorios rurales. | D5: La concentración de la tierra, la exclusión política y social, la desigualdad económica y la débil presencia estatal en zonas rurales son las causas estructurales que, según la Comisión de la Verdad, desencadenaron el conflicto armado en Colombia. | E5: 3444 | F5: 811 | G5: 411
A6: ¿Qué dice este informe 058-CI-00661 «Informe sobre el conflicto social y armado en el suroeste de Antioquia» sobre las causas estructurales del conflicto armado y sus recomendaciones para la no repetición? | B6: El informe identifica como causas estructurales del conflicto la desigualdad en el acceso a la tierra, la exclusión política, la represión de los movimientos sociales, la concentración del poder económico y político, y la criminalización de la protesta. También señala la influencia del modelo económico extractivista que favorece a intereses corporativos sobre los derechos de las comunidades. Entre las recomendaciones para la no repetición, se propone garantizar el derecho a la tierra, fortalecer la participación democrática, reconocer y proteger a las organizaciones sociales, esclarecer los hechos del pasado, y garantizar justicia y reparación integral para las víctimas. | C6: El informe atribuye el conflicto a causas estructurales como la concentración de la tierra, exclusión política, represión estatal y modelo económico extractivista. Recomienda asegurar derechos territoriales, participación política efectiva, memoria, verdad, justicia y garantías de no repetición para las víctimas y comunidades. | D6: El informe 058-CI-00661 «Informe sobre el conflicto social y armado en el suroeste de Antioquia» destaca que las causas estructurales del conflicto armado en Colombia incluyen la desigualdad en el acceso a la tierra, la exclusión política, la represión de los movimientos sociales, la concentración del poder económico y político, y la criminalización de la protesta. Además, subraya la influencia del modelo económico extractivista que favorece a intereses corporativos sobre los derechos de las comunidades. Entre sus recomendaciones para la no repetición, se incluyen garantizar el derecho a la tierra, fortalecer la participación democrática, reconocer y proteger a las organizaciones sociales, esclarecer los | E6: 9886 | F6: 0,75 | G6: 327
A7: ¿Cuáles son los hallazgos principales del informe 058-CI-00662 «Memoria y construcción de paz en el sector cooperativo del oriente antioqueño: estudio de caso de las cooperativas Coogranada, Creafam, Confiar, Pío XII y Coosanluis entre 1991 y 2016» sobre el conflicto armado colombiano? | B7: El informe 058-CI-00662 «Memoria y construcción de paz en el sector cooperativo» señala que el Movimiento Solidario y Cooperativo del Oriente Antioqueño fue uno de los sectores más golpeados por el conflicto armado. A pesar de ello, cumplió un papel protagónico al desplegar acciones de resistencia y apoyo a las comunidades desplazadas. Las cooperativas enfrentaron tomas armadas, desplazamiento forzado, confinamiento, extorsión e intimidación, pero lograron mantener su operación mediante estrategias de sostenibilidad, expansión y fortalecimiento del tejido social. Se destaca el apoyo a las personas asociadas mediante la condonación de deudas, créditos especiales y reconstrucción física de los municipios. | C7: El informe documenta que las cooperativas del Oriente Antioqueño fueron gravemente afectadas por el conflicto armado mediante desplazamientos forzados, violencia directa a empleados y asociados, y presiones de actores armados. No obstante, desempeñaron un papel clave en la resistencia civil, apoyando a comunidades desplazadas y contribuyendo a la reconstrucción del tejido social mediante estrategias económicas solidarias y acciones comunitarias. | D7: El informe 058-CI-00662 «Memoria y construcción de paz en el sector cooperativo» revela que el Movimiento Solidario y Cooperativo del Oriente Antioqueño fue uno de los sectores más afectados por el conflicto armado. A pesar de las dificultades, las cooperativas desplegaron acciones de resistencia y apoyo a las comunidades desplazadas. Se enfrentaron a tomas armadas, desplazamiento forzado, confinamiento, extorsión e intimidación, pero mantuvieron su operación mediante estrategias de sostenibilidad, expansión y fortalecimiento del tejido social. Se destaca el apoyo a las personas asociadas mediante la condonación de deudas, créditos especiales y reconstrucción física | E7: 9861 | F7: 762 | G7: 325
A8: ¿Qué tipo de violencia vivieron las cooperativas del Oriente Antioqueño entre 1991 y 2016 según el informe? | B8: El informe 058-CI-00662 «Memoria y construcción de paz en el sector cooperativo» detalla que las cooperativas fueron blanco de diversas acciones violentas durante el conflicto armado. Estas incluyeron asesinatos de empleados, familiares y asociados; robos e intentos de extorsión; y violencia psicológica e intimidación por parte de grupos armados. Estos actos no solo afectaron el funcionamiento de las cooperativas, sino que también contribuyeron al empobrecimiento de sus comunidades asociadas y al desplazamiento forzado masivo. | C8: Las cooperativas del Oriente Antioqueño vivieron asesinatos selectivos de su personal y asociados, robos, extorsión, amenazas e intimidación psicológica por parte de actores armados. Estas formas de violencia afectaron gravemente su funcionamiento institucional, provocaron desplazamiento forzado y contribuyeron a la descomposición del tejido social de las comunidades cooperadas. | D8: Las cooperativas del Oriente Antioqueño fueron víctimas de asesinatos, robos, extorsiones, violencia psicológica e intimidación, lo que generó un ambiente de miedo y desconfianza, afectando su estabilidad económica y social. | E8: 3442 | F8: 806 | G8: 385
A9: ¿Qué dice este informe 365-CI-00941 La participación de pueblos indígenas en justicia transicional - ¿oportunidad de cambios? Aprendizajes de Colombia sobre las causas estructurales del conflicto armado y sus recomendaciones para la no repetición? | B9: El informe 365-CI-00941 La participación de pueblos indígenas en justicia transicional resalta que una reconciliación multinacional, multicultural y multiétnica es esencial para asegurar la no repetición. Plantea que deben transformarse las estructuras que perpetúan la dominación étnica y que el diálogo debe incluir múltiples dimensiones socio-culturales【4:8†source】. | C9: El informe propone dialogar y revisar estructuras socio-culturales como medidas claves para la no repetición y aborda las causas estructurales del conflicto desde la perspectiva de dominación étnica y falta de reconocimiento multicultural. | D9: El informe 365-CI-00941 La participación de pueblos indígenas en justicia transicional - ¿oportunidad de cambios? Aprendizajes de Colombia sobre las causas estructurales del conflicto armado y sus recomendaciones para la no repetición? reconoce que la justicia transicional debe integrar la diversidad étnica y cultural para asegurar una paz inclusiva. Destaca la importancia de abordar las causas estructurales del conflicto, como la discriminación y la exclusión, y propone mecanismos de participación indígena en la construcción de un país más equitativo. | E9: 7976 | F9: 733 | G9: 281
A10: ¿Cómo el sistema de justicia transicional puede beneficiar a los pueblos indígenas en el contexto colombiano según el informe 365-CI-00941? | B10: El Sistema Integral de Verdad, Justicia, Reparación y No Repetición (SIVJRNR) está diseñado para satisfacer el derecho a la verdad, justicia y reparación, aunque la implementación efectiva es cuestionada por la falta de recursos y capacitación adecuada【4:7†source】. | C10: El sistema de justicia transicional tiene el potencial de beneficiar a los pueblos indígenas al proporcionar verdad, justicia y reparación, pero enfrenta desafíos significativos en su implementación debido a recursos limitados. | D10: El sistema de justicia transicional puede beneficiar a los pueblos indígenas al reconocer y reparar los daños históricos y actuales, promoviendo la restitución de tierras y la protección de sus derechos culturales y territoriales【4:7†source】. | E10: 3315 | F10: 779 | G10: 353
A11: ¿Cuáles son los hallazgos principales del informe «365-CI-00942 Bitácora de la guerra sucia» sobre graves violaciones a los derechos humanos e infracciones al Derecho Internacional Humanitario cometidas en el Departamento del Cauca entre los años 2006–2016? | B11: «365-CI-00942 Bitácora de la guerra sucia» es un informe que evidencia violaciones sistemáticas a los derechos humanos cometidas por diferentes actores armados en el Departamento del Cauca, principalmente por la Fuerza Pública, grupos paramilitares y grupos sucesores del paramilitarismo. Destaca la persistencia del paramilitarismo y el uso de la violencia por parte del Estado y actores armados para influir en el modelo de Estado o sociedad vigente. Se documentan casos de ejecuciones extrajudiciales, masacres, torturas y desplazamientos forzados, entre otros. | C11: El informe «365-CI-00942 Bitácora de la guerra sucia» revela graves violaciones a los derechos humanos en el Cauca, cometidas por la Fuerza Pública, grupos paramilitares y sus sucesores, incluyendo ejecuciones extrajudiciales, masacres, torturas y desplazamientos forzados; evidencia la persistencia del paramilitarismo y el uso de la violencia para mantener el statu quo social y político. | D11: Los hallazgos principales del informe «365-CI-00942 Bitácora de la guerra sucia» sobre graves violaciones a los derechos humanos e infracciones al Derecho Internacional Humanitario en el Departamento del Cauca entre 2006 y 2016 incluyen: a) Violaciones sistemáticas a los derechos humanos por parte de la Fuerza Pública, grupos paramilitares y grupos sucesores del paramilitarismo; b) Persistencia del paramilitarismo y uso de la violencia para influir en el modelo de Estado o sociedad vigente; c) Documentación de casos de ejecuciones extrajudiciales, masacres, torturas y desplazamientos forzados, entre otros. | E11: 9859 | F11: 839 | G11: 507
A12: ¿Cuáles son los hallazgos principales del informe «365-CI-01666 Aportes para la implementación del enfoque extraterritorial» sobre el conflicto armado colombiano? | B12: El informe «365-CI-01666 Aportes para la implementación del enfoque extraterritorial» de la Comisión para el Esclarecimiento de la Verdad, la Convivencia y la No Repetición destaca la persistencia de graves violaciones a los derechos humanos y al Derecho Internacional Humanitario durante el conflicto armado colombiano, incluyendo desplazamiento forzado, desapariciones forzadas, violencia sexual, asesinatos y reclutamiento de menores. Subraya el impacto diferencial sobre diversos grupos, especialmente mujeres, comunidades indígenas, afrodescendientes y personas defensoras de derechos humanos. El enfoque extraterritorial busca visibilizar las experiencias de las víctimas en el exilio, señalando obstáculos en el acceso a la verdad, justicia y reparación, derivados tanto de la distancia territorial como de barreras institucionales y sociales en los países de acogida. | C12: El informe «365-CI-01666 Aportes para la implementación del enfoque extraterritorial» señala que el conflicto armado generó violaciones graves a los derechos humanos que afectaron desproporcionadamente a grupos vulnerables. Destaca la necesidad de visibilizar y atender las demandas de las víctimas en el exilio, quienes enfrentan limitaciones adicionales para acceder a la verdad, la justicia y la reparación, y subraya la importancia de un enfoque extraterritorial que reconozca el carácter transnacional del daño e impulse garantías de no repetición. | D12: El informe «365-CI-01666 Aportes para la implementación del enfoque extraterritorial» de la Comisión para el Esclarecimiento de la Verdad, la Convivencia y la No Repetición destaca la persistencia de graves violaciones a los derechos humanos y al Derecho Internacional Humanitario durante el conflicto armado colombiano, incluyendo desplazamiento forzado, desapariciones forzadas, violencia sexual, asesinatos y reclutamiento de menores. Subraya el impacto diferencial sobre diversos grupos, especialmente mujeres, comunidades indígenas, afrodescendientes y personas defensoras de derechos humanos. El enfoque extraterritorial busca visibilizar las experiencias de las víctimas en el exilio, señalando obstáculos | E12: 9898 | F12: 787 | G12: 384
A13: ¿Cuáles son los hallazgos principales del informe «365-CI-01666 Aportes para la implementación del enfoque extraterritorial» sobre el conflicto armado colombiano? | B13: El informe «365-CI-01666 Aportes para la implementación del enfoque extraterritorial» argumenta que las víctimas exiliadas como resultado del conflicto armado colombiano poseen necesidades específicas derivadas de su desplazamiento internacional, sufriendo la pérdida de derechos, disolución de tejidos comunitarios y obstáculos a la participación política en Colombia. Señala la invisibilización de estas víctimas en los procesos oficiales de esclarecimiento, reparación y justicia, y la urgencia de incorporar políticas inclusivas que reconozcan la dimensión extraterritorial del conflicto. | C13: El informe «365-CI-01666 Aportes para la implementación del enfoque extraterritorial» identifica que las víctimas en el exilio han sido sistemáticamente invisibilizadas en los procesos de verdad y reparación y enfrentan barreras adicionales para acceder a sus derechos. Recomienda ampliar el enfoque institucional para cubrir la dimensión transnacional del conflicto y reconocer a las víctimas en el exilio como sujetos plenos de derechos en las políticas de verdad, reparación y garantías de no repetición. | D13: El informe «365-CI-01666 Aportes para la implementación del enfoque extraterritorial» destaca que las víctimas del conflicto armado colombiano que se encuentran en el exilio enfrentan desafíos específicos, como la pérdida de derechos, la fragmentación de redes sociales y la dificultad de acceder a mecanismos de reparación y justicia en Colombia. El informe subraya la necesidad de implementar políticas que visibilicen y atiendan las necesidades de estas víctimas, integrando el enfoque extraterritorial en los procesos de paz y justicia transicional. | E13: 7893 | F13: 832 | G13: 372
A14: ¿Qué señala el informe «365-CI-01666 Aportes para la implementación del enfoque extraterritorial» sobre las causas estructurales del conflicto armado y sus recomendaciones para la no repetición? | B14: El informe «365-CI-01666 Aportes para la implementación del enfoque extraterritorial» explica que entre las causas estructurales del conflicto armado colombiano se encuentran la exclusión política, la desigualdad social y económica, la concentración de la tierra y la falta de garantías para el ejercicio de derechos fundamentales. En cuanto a las recomendaciones para la no repetición, enfatiza la importancia de garantizar la inclusión de las víctimas en el exilio en las políticas públicas, fortalecer los mecanismos de reparación integral, asegurar la no discriminación y promover la construcción de paz desde un enfoque de derechos humanos tanto en Colombia como en los países receptores. | C14: El informe «365-CI-01666 Aportes para la implementación del enfoque extraterritorial» identifica como causas estructurales del conflicto factores como la exclusión política, la concentración de la tierra, la desigualdad social y la falta de garantías de derechos. Para evitar la repetición, recomienda políticas que reconozcan el impacto extraterritorial del conflicto, garanticen la reparación integral de las víctimas en el exilio, promuevan la inclusión social y política y refuercen el enfoque de derechos humanos en la construcción de paz. | D14: El informe «365-CI-01666 Aportes para la implementación del enfoque extraterritorial» destaca que las causas estructurales del conflicto armado colombiano incluyen la exclusión política, la desigualdad social y económica, la concentración de la tierra y la falta de garantías para el ejercicio de derechos fundamentales. Entre las recomendaciones para la no repetición, se destacan la inclusión de las víctimas en el exilio en las políticas públicas, el fortalecimiento de los mecanismos de reparación integral, la garantía de no discriminación y la promoción de la construcción de paz desde un enfoque de derechos humanos tanto en Colombia como en los países receptores. | E14: 9376 | F14: 827 | G14: 442
A15: ¿Cuáles son los hallazgos principales del informe «748-CI-00629 Contextos explicativos del desplazamiento forzado en el sur del Tolima: impactos sobre el territorio y la territorialidad 1958–2018» sobre el conflicto armado colombiano? | B15: El informe «748-CI-00629 Contextos explicativos del desplazamiento forzado en el sur del Tolima: impactos sobre el territorio y la territorialidad 1958–2018» señala que el territorio del sur del Tolima fue escenario de múltiples disputas entre grupos armados ilegales, generando un clima constante de amenaza, persecución y violencia. La población civil sufrió desplazamientos sucesivos y se registraron episodios masivos ligados a operaciones militares, acciones paramilitares y enfrentamientos guerrilleros. Además, se evidencia que la respuesta estatal fue insuficiente para garantizar la protección y el retorno seguro de las personas desplazadas. | C15: El informe «748-CI-00629 Contextos explicativos del desplazamiento forzado en el sur del Tolima: impactos sobre el territorio y la territorialidad 1958–2018» revela que la multiplicidad de actores armados y la falta de protección estatal ocasionaron desplazamientos masivos y recurrentes, afectando particularmente a comunidades rurales, y subraya la necesidad de fortalecer la presencia y respuesta institucional para evitar la repetición de estos hechos violentos. | D15: El informe «748-CI-00629 Contextos explicativos del desplazamiento forzado en el sur del Tolima: impactos sobre el territorio y la territorialidad 1958–2018» destaca que el desplazamiento forzado en el sur del Tolima se debe a la combinación de factores como la violencia de grupos armados ilegales, las operaciones militares y la falta de respuesta estatal. Se identifican contextos históricos de desplazamiento masivo, especialmente en los años 1990 y 2000, y se subraya la persistencia de amenazas y violencias que afectan la territorialidad de la población. | E15: 9,35 | F15: 827 | G15: 379
A16: ¿Cuáles fueron los principales episodios de desplazamiento forzado documentados en el informe «748-CI-00629 Contextos explicativos del desplazamiento forzado en el sur del Tolima: impactos sobre el territorio y la territorialidad 1958–2018» entre 1958 y 2018? | B16: El informe «748-CI-00629 Contextos explicativos del desplazamiento forzado en el sur del Tolima: impactos sobre el territorio y la territorialidad 1958–2018» describe casos emblemáticos de desplazamiento forzado como el ocurrido en el municipio de Planadas durante los años ochenta y noventa, cuando cientos de familias abandonaron sus hogares debido a confrontaciones entre el Ejército y las fuerzas guerrilleras. Incluye testimonios de líderes comunitarios que relatan el miedo y la zozobra vivida, así como la ocupación de territorios por actores ilegales que imposibilitaron el retorno seguro de las comunidades. | C16: En el informe «748-CI-00629 Contextos explicativos del desplazamiento forzado en el sur del Tolima: impactos sobre el territorio y la territorialidad 1958–2018», los principales episodios documentados incluyen acciones militares y hostigamientos de grupos armados ilegales en municipios como Planadas, donde las comunidades se vieron obligadas a abandonar sus tierras ante el riesgo inminente de violencia, afectando profundamente su arraigo territorial y proyecto de vida. | D16: El informe documenta episodios de desplazamiento forzado como el de Planadas, donde entre 1980 y 2000, la violencia entre el Ejército y la guerrilla del ELN y el M-19 obligó a más de 300 familias a abandonar sus tierras. Además, se menciona el caso de la vereda La Unión en el municipio de Rovira, donde en 2002, la presencia de grupos paramilitares y enfrentamientos armados entre estos y la guerrilla del ELN, provocaron el desplazamiento de 150 familias. En 2018, el informe también registra el desplazamiento de 10 familias de la vereda La Esperanza | E16: 9878 | F16: 712 | G16: 272
A17: ¿Qué relación establece el informe «748-CI-00629 Contextos explicativos del desplazamiento forzado en el sur del Tolima: impactos sobre el territorio y la territorialidad 1958–2018» entre el control territorial por parte de actores armados y las transformaciones en las dinámicas agrarias y sociales del sur del Tolima? | B17: El informe «748-CI-00629 Contextos explicativos del desplazamiento forzado en el sur del Tolima: impactos sobre el territorio y la territorialidad 1958–2018» vincula en varios apartados el control territorial ejercido por actores armados ilegales con la imposición de nuevas dinámicas económicas y sociales. Señala que este control facilitó cambios en los modos de producción agrícola, la sustitución de cultivos tradicionales por economías ilícitas y la fragmentación del tejido social, lo que dificultó la organización comunitaria y la defensa de los derechos colectivos. | C17: El informe «748-CI-00629 Contextos explicativos del desplazamiento forzado en el sur del Tolima: impactos sobre el territorio y la territorialidad 1958–2018» establece que la presencia y control territorial de grupos armados ilegales provocaron transformaciones en la estructura agraria, el surgimiento de economías ilícitas y una mayor vulnerabilidad de las comunidades frente a la violencia y la desprotección estatal. | D17: El informe establece que el control territorial ejercido por actores armados ilegales ha sido un factor determinante en la imposición de nuevas dinámicas económicas y sociales en el sur del Tolima. Este control ha permitido la sustitución de cultivos tradicionales por economías ilícitas, la fragmentación del tejido social y la imposición de nuevas formas de producción agrícola, lo que ha dificultado la organización comunitaria y la defensa de los derechos colectivos. | E17: 6351 | F17: 0,76 | G17: 258
A18: ¿Qué dice el informe «748-CI-00855 La sombra oscura del banano: Urabá. conflicto armado y el rol del empresariado» sobre las causas estructurales del conflicto armado y sus recomendaciones para la no repetición? | B18: El informe «748-CI-00855 La sombra oscura del banano: Urabá. conflicto armado y el rol del empresariado» señala que las causas estructurales del conflicto armado en Urabá incluyen la concentración de la tierra, las históricas desigualdades sociales, la falta de garantías para los derechos laborales y la ausencia de regulación estatal efectiva sobre el sector bananero. Estas condiciones facilitaron la injerencia de actores armados ilegales y la consolidación de economías extractivas violentas. Entre las recomendaciones, el informe propone fortalecer la presencia estatal, garantizar la protección de los derechos humanos, implementar mecanismos de reparación y memoria histórica y promover la participación de las comunidades en la toma de decisiones para asegurar la no repetición de la violencia. | C18: El informe «748-CI-00855 La sombra oscura del banano: Urabá. conflicto armado y el rol del empresariado» atribuye el conflicto armado en Urabá a factores como la concentración de la tierra, las desigualdades sociales históricas y la ausencia de regulación estatal en el sector bananero, y recomienda fortalecer la institucionalidad, garantizar la protección de los derechos humanos, impulsar mecanismos de reparación y memoria histórica y promover la participación comunitaria como garantías de no repetición. | D18: El informe «748-CI-00855 La sombra oscura del banano: Urabá. conflicto armado y el rol del empresariado» destaca que las causas estructurales del conflicto armado en Urabá incluyen la concentración de la tierra, las desigualdades sociales, la falta de garantías laborales y la ausencia de regulación estatal. Estas condiciones permitieron la injerencia de actores armados ilegales y la consolidación de economías violentas. El informe recomienda fortalecer la presencia estatal, garantizar la protección de derechos humanos, implementar mecanismos de reparación y memoria histórica, y promover la participación comunitaria para asegurar la no repetición de la violencia. | E18: 9753 | F18: 846 | G18: 491
A19: ¿Cuáles son los hallazgos principales del informe «748-CI-00857 Análisis policías víctimas del conflicto armado interno» sobre el conflicto armado colombiano? | B19: El informe «748-CI-00857 Análisis policías víctimas del conflicto armado interno» presenta un análisis sobre el impacto del conflicto en los miembros de la Policía Nacional, destacando cifras de homicidios, desapariciones forzadas, secuestros y otros hechos victimizantes a lo largo de varias décadas. Señala que la violencia ejercida por grupos armados ilegales contra la Policía fue sistemática, constituyendo graves violaciones a los derechos humanos y al Derecho Internacional Humanitario, especialmente en zonas de alta confrontación. También documenta desplazamientos forzados, reclutamiento, amenazas y estigmatización sufridos por los uniformados y sus familias. | C19: El informe «748-CI-00857 Análisis policías víctimas del conflicto armado interno» revela que los policías sufrieron múltiples formas de victimización, incluyendo homicidios, desapariciones forzadas, secuestros, desplazamientos forzados, amenazas y estigmatización, perpetradas de manera sistemática por grupos armados ilegales y generando graves impactos en los uniformados y sus familias. | D19: El informe «748-CI-00857 Análisis policías víctimas del conflicto armado interno» revela que entre 1984 y 2014, 1.180 policías fueron víctimas del conflicto armado interno, de los cuales 720 resultaron muertos. Se identifican 120 casos de secuestro, 100 de desaparición forzada y 100 de homicidio. Además, se documentan 1.000 casos de amenazas, 1.000 de estigmatización y 500 de reclutamiento forzado. El informe concluye que la violencia contra la Policía fue sistemática y | E19: 9766 | F19: 796 | G19: 0,32
A20: ¿Cuáles son los principales tipos de victimización sufridos por policías durante el conflicto armado según el informe «748-CI-00857 Análisis policías víctimas del conflicto armado interno»? | B20: El informe «748-CI-00857 Análisis policías víctimas del conflicto armado interno» detalla que los miembros de la Policía Nacional fueron víctimas de homicidios selectivos, desapariciones forzadas, secuestros, desplazamientos forzados, amenazas, atentados y ataques directos a instalaciones policiales. Estos hechos provocaron un fuerte impacto psicológico y social en las familias de los policías y en sus comunidades. | C20: El informe «748-CI-00857 Análisis policías víctimas del conflicto armado interno» establece que los policías fueron víctimas de homicidios selectivos, desapariciones forzadas, secuestros, desplazamientos forzados, amenazas y ataques a instalaciones policiales, lo que generó daños a nivel psicológico, social y familiar. | D20: Los principales tipos de victimización sufridos por policías durante el conflicto armado, según el informe «748-CI-00857 Análisis policías víctimas del conflicto armado interno», incluyen homicidios selectivos, desapariciones forzadas, secuestros, desplazamientos forzados, amenazas, atentados y ataques directos a instalaciones policiales. Estos hechos generaron un profundo impacto psicológico y social en las familias de los policías y en sus comunidades. | E20: 6814 | F20: 872 | G20: 569
A21: ¿Qué dice el informe «119-CI-00336 La maldita tierra: guerrilla, paramilitares, mineras y conflicto armado en el departamento del Cesar» sobre las causas estructurales del conflicto armado y sus recomendaciones para la no repetición? | B21: El informe «119-CI-00336 La maldita tierra: guerrilla, paramilitares, mineras y conflicto armado en el departamento del Cesar» identifica factores como la inequidad en la tenencia de la tierra, la influencia desmedida de élites económicas y políticas, y la falta de intervención estatal efectiva como causas estructurales. Recomienda una reforma agraria justa y una mayor transparencia en las concesiones mineras para evitar futuros conflictos. | C21: El informe «119-CI-00336 La maldita tierra: guerrilla, paramilitares, mineras y conflicto armado en el departamento del Cesar» sugiere que la resolución del conflicto armado requiere abordar profundamente la disparidad en la distribución de tierras y controlar el poder excesivo de las élites locales. Recomienda implementar una reforma agraria equitativa y reglamentar estrictamente las actividades mineras para prevenir la repetición de conflictos. | D21: El informe «119-CI-00336 La maldita tierra: guerrilla, paramilitares, mineras y conflicto armado en el departamento del Cesar» destaca la inequidad en la tenencia de la tierra, la influencia desmedida de élites económicas y políticas, y la falta de intervención estatal efectiva como causas estructurales del conflicto armado. Recomienda una reforma agraria justa, mayor transparencia en las concesiones mineras, y la implementación de políticas que fortalezcan la participación ciudadana y el control social sobre los recursos naturales para prevenir futuros conflictos. | E21: 8477 | F21: 819 | G21: 0,4
A22: ¿Cuáles son los hallazgos principales del informe «119-CI-00339 Tierra y carbón en la vorágine del Gran Magdalena: los casos de las parcelaciones de El Toco, El Platanal y Santa Fe» sobre el conflicto armado colombiano? | B22: El informe «119-CI-00339 Tierra y carbón en la vorágine del Gran Magdalena: los casos de las parcelaciones de El Toco, El Platanal y Santa Fe» describe casos emblemáticos de despojo que se combinaron con acciones contrainsurgentes y un reordenamiento violento del territorio para la transición a economías carboníferas y agroindustriales. La región fue testigo de masacres y desplazamientos que facilitaron la imposición de un nuevo orden territorial en beneficio de multinacionales y agroindustriales. Los actores con privilegios participaron activamente para dar apariencia de legalidad a la contrarreforma agraria impuesta violentamente. | C22: El informe «119-CI-00339 Tierra y carbón en la vorágine del Gran Magdalena: los casos de las parcelaciones de El Toco, El Platanal y Santa Fe» revela un patrón sistemático de despojo y desplazamiento forzado, impulsado por intereses económicos relacionados con la minería y la agroindustria, facilitado por acciones paramilitares y avalado por élites políticas y económicas. Destaca la violencia utilizada para reconfigurar territorios mediante masacres y desplazamientos, beneficiando a multinacionales y agroindustriales en perjuicio de los derechos de los campesinos. | D22: El informe «119-CI-00339 Tierra y carbón en la vorágine del Gran Magdalena: los casos de las parcelaciones de El Toco, El Platanal y Santa Fe» revela que el conflicto armado en la región se manifestó a través de masacres, desplazamientos forzados y acciones contrainsurgentes que permitieron el despojo de tierras y la imposición de un nuevo orden territorial. Este proceso benefició a multinacionales y agroindustriales, quienes, con el apoyo de actores con privilegios, dieron apariencia de legalidad a la contrarreforma agraria impuesta violentamente. | E22: 9021 | F22: 829 | G22: 395
